[
  {
    "title": "Inside CrowdStrike&rsquo;s Science-Backed Approach to Building Expert SOC Agents",
    "url": "https://www.crowdstrike.com/en-us/blog/inside-crowdstrikes-science-backed-approach-to-building-soc-agents/",
    "snippet": "Gemini unavailable – default relevance.",
    "source": "crowdstrike.com",
    "time": "2026-01-15T12:52:35.574371+00:00",
    "region": "Global",
    "severity": 2,
    "type": "PHYSICAL SECURITY"
  },
  {
    "title": "CrowdTour 2026: Securing the AI Era Together",
    "url": "https://www.crowdstrike.com/en-us/blog/crowdtour-2026-securing-ai-era-together/",
    "snippet": "Gemini unavailable – default relevance.",
    "source": "crowdstrike.com",
    "time": "2026-01-15T12:52:35.574338+00:00",
    "region": "Global",
    "severity": 2,
    "type": "PHYSICAL SECURITY"
  },
  {
    "title": "How CrowdStrike Trains GenAI Models at Scale Using Distributed Computing",
    "url": "https://www.crowdstrike.com/en-us/blog/how-crowdstrike-trains-genai-models-at-scale-using-distributed-computing/",
    "snippet": "Gemini unavailable – default relevance.",
    "source": "crowdstrike.com",
    "time": "2026-01-15T12:52:35.574309+00:00",
    "region": "Global",
    "severity": 2,
    "type": "PHYSICAL SECURITY"
  },
  {
    "title": "Streamline Security Operations with Falcon for IT&rsquo;s Turnkey Automations",
    "url": "https://www.crowdstrike.com/en-us/blog/streamline-security-operations-falcon-for-it-automations/",
    "snippet": "Gemini unavailable – default relevance.",
    "source": "crowdstrike.com",
    "time": "2026-01-15T12:52:35.574277+00:00",
    "region": "Global",
    "severity": 2,
    "type": "PHYSICAL SECURITY"
  },
  {
    "title": "CrowdStrike&rsquo;s Journey in Customizing NVIDIA Nemotron Models for Peak Accuracy and Performance",
    "url": "https://www.crowdstrike.com/en-us/blog/crowdstrike-journey-in-customizing-nvidia-nemotron-models/",
    "snippet": "Gemini unavailable – default relevance.",
    "source": "crowdstrike.com",
    "time": "2026-01-15T12:52:35.574244+00:00",
    "region": "Global",
    "severity": 2,
    "type": "PHYSICAL SECURITY"
  },
  {
    "title": "How CrowdStrike&rsquo;s Malware Analysis Agent Detects Malware at Machine Speed",
    "url": "https://www.crowdstrike.com/en-us/blog/how-crowdstrike-detects-malware-at-machine-speed/",
    "snippet": "Gemini unavailable – default relevance.",
    "source": "crowdstrike.com",
    "time": "2026-01-15T12:52:35.574207+00:00",
    "region": "Global",
    "severity": 2,
    "type": "PHYSICAL SECURITY"
  },
  {
    "title": "CrowdStrike to Acquire SGNL to Secure Every Identity in the AI Era",
    "url": "https://www.crowdstrike.com/en-us/blog/crowdstrike-to-acquire-sgnl/",
    "snippet": "Gemini unavailable – default relevance.",
    "source": "crowdstrike.com",
    "time": "2026-01-15T12:52:35.574172+00:00",
    "region": "Global",
    "severity": 2,
    "type": "PHYSICAL SECURITY"
  },
  {
    "title": "AI Tool Poisoning: How Hidden Instructions Threaten AI Agents",
    "url": "https://www.crowdstrike.com/en-us/blog/ai-tool-poisoning/",
    "snippet": "Gemini unavailable – default relevance.",
    "source": "crowdstrike.com",
    "time": "2026-01-15T12:52:35.574136+00:00",
    "region": "Global",
    "severity": 2,
    "type": "PHYSICAL SECURITY"
  },
  {
    "title": "January 2026 Patch Tuesday: 114 CVEs Patched Including 3 Zero-Days",
    "url": "https://www.crowdstrike.com/en-us/blog/patch-tuesday-analysis-january-2026/",
    "snippet": "Gemini unavailable – default relevance.",
    "source": "crowdstrike.com",
    "time": "2026-01-15T12:52:35.574101+00:00",
    "region": "Global",
    "severity": 2,
    "type": "PHYSICAL SECURITY"
  },
  {
    "title": "CrowdStrike to Acquire Seraphic to Secure Work in Any Browser",
    "url": "https://www.crowdstrike.com/en-us/blog/crowdstrike-to-acquire-seraphic/",
    "snippet": "Gemini unavailable – default relevance.",
    "source": "crowdstrike.com",
    "time": "2026-01-15T12:52:35.574053+00:00",
    "region": "Global",
    "severity": 2,
    "type": "PHYSICAL SECURITY"
  },
  {
    "title": "M 1.2 - 18 km WSW of Johannesburg, CA",
    "url": "https://earthquake.usgs.gov/earthquakes/eventpage/ci41158599",
    "snippet": "Gemini unavailable – default relevance.",
    "source": "earthquake.usgs.gov",
    "time": "2026-01-15T12:52:31.648846+00:00",
    "region": "Global",
    "severity": 2,
    "type": "PHYSICAL SECURITY"
  },
  {
    "title": "M 2.2 - 7 km WSW of Holtville, CA",
    "url": "https://earthquake.usgs.gov/earthquakes/eventpage/ci41158607",
    "snippet": "Gemini unavailable – default relevance.",
    "source": "earthquake.usgs.gov",
    "time": "2026-01-15T12:52:31.648548+00:00",
    "region": "Global",
    "severity": 2,
    "type": "PHYSICAL SECURITY"
  },
  {
    "title": "M 2.3 - 7 km WSW of Holtville, CA",
    "url": "https://earthquake.usgs.gov/earthquakes/eventpage/ci41158615",
    "snippet": "Gemini unavailable – default relevance.",
    "source": "earthquake.usgs.gov",
    "time": "2026-01-15T12:52:31.648266+00:00",
    "region": "Global",
    "severity": 2,
    "type": "PHYSICAL SECURITY"
  },
  {
    "title": "M 1.9 - 8 km WSW of Holtville, CA",
    "url": "https://earthquake.usgs.gov/earthquakes/eventpage/ci41158631",
    "snippet": "Gemini unavailable – default relevance.",
    "source": "earthquake.usgs.gov",
    "time": "2026-01-15T12:52:31.647983+00:00",
    "region": "Global",
    "severity": 2,
    "type": "PHYSICAL SECURITY"
  },
  {
    "title": "M 4.9 - 36 km NE of Meiktila, Burma (Myanmar)",
    "url": "https://earthquake.usgs.gov/earthquakes/eventpage/us7000rpuq",
    "snippet": "Gemini unavailable – default relevance.",
    "source": "earthquake.usgs.gov",
    "time": "2026-01-15T12:52:31.647698+00:00",
    "region": "Global",
    "severity": 2,
    "type": "PHYSICAL SECURITY"
  },
  {
    "title": "M 1.7 - 7 km WSW of Holtville, CA",
    "url": "https://earthquake.usgs.gov/earthquakes/eventpage/ci41158639",
    "snippet": "Gemini unavailable – default relevance.",
    "source": "earthquake.usgs.gov",
    "time": "2026-01-15T12:52:31.647394+00:00",
    "region": "Global",
    "severity": 2,
    "type": "PHYSICAL SECURITY"
  },
  {
    "title": "M 1.6 - 7 km WSW of Holtville, CA",
    "url": "https://earthquake.usgs.gov/earthquakes/eventpage/ci41158647",
    "snippet": "Gemini unavailable – default relevance.",
    "source": "earthquake.usgs.gov",
    "time": "2026-01-15T12:52:31.647106+00:00",
    "region": "Global",
    "severity": 2,
    "type": "PHYSICAL SECURITY"
  },
  {
    "title": "M 1.0 - 6 km WNW of Cobb, CA",
    "url": "https://earthquake.usgs.gov/earthquakes/eventpage/nc75296101",
    "snippet": "Gemini unavailable – default relevance.",
    "source": "earthquake.usgs.gov",
    "time": "2026-01-15T12:52:31.646810+00:00",
    "region": "Global",
    "severity": 2,
    "type": "PHYSICAL SECURITY"
  },
  {
    "title": "M 1.6 - 5 km SW of Holtville, CA",
    "url": "https://earthquake.usgs.gov/earthquakes/eventpage/ci41158655",
    "snippet": "Gemini unavailable – default relevance.",
    "source": "earthquake.usgs.gov",
    "time": "2026-01-15T12:52:31.646455+00:00",
    "region": "Global",
    "severity": 2,
    "type": "PHYSICAL SECURITY"
  },
  {
    "title": "Philippines and Japan sign security agreement as regional tensions rise",
    "url": "https://asia.nikkei.com/politics/defense/philippines-and-japan-sign-security-agreement-as-regional-tensions-rise",
    "snippet": "Gemini unavailable – default relevance.",
    "source": "asia.nikkei.com",
    "time": "2026-01-15T12:52:19.925355+00:00",
    "region": "APJC",
    "severity": 2,
    "type": "PHYSICAL SECURITY"
  },
  {
    "title": "TSMC plans record capex of up to $56bn 2026 amid AI boom",
    "url": "https://asia.nikkei.com/business/tech/semiconductors/tsmc-plans-record-capex-of-up-to-56bn-2026-amid-ai-boom",
    "snippet": "Gemini unavailable – default relevance.",
    "source": "asia.nikkei.com",
    "time": "2026-01-15T12:52:19.925328+00:00",
    "region": "Global",
    "severity": 2,
    "type": "PHYSICAL SECURITY"
  },
  {
    "title": "ASICS opens Onitsuka Tiger plant to showcase pricey sneakers",
    "url": "https://asia.nikkei.com/business/companies/asics-opens-onitsuka-tiger-plant-to-showcase-pricey-sneakers",
    "snippet": "Gemini unavailable – default relevance.",
    "source": "asia.nikkei.com",
    "time": "2026-01-15T12:52:19.925295+00:00",
    "region": "EMEA",
    "severity": 2,
    "type": "PHYSICAL SECURITY"
  },
  {
    "title": "Trip.com stock falls 19% as group faces China antitrust probe",
    "url": "https://asia.nikkei.com/business/companies/trip.com-stock-falls-19-as-group-faces-china-antitrust-probe",
    "snippet": "Gemini unavailable – default relevance.",
    "source": "asia.nikkei.com",
    "time": "2026-01-15T12:52:19.925267+00:00",
    "region": "APJC",
    "severity": 2,
    "type": "PHYSICAL SECURITY"
  },
  {
    "title": "Indonesia cracks down on industrial tax cheats as fiscal deficit widens",
    "url": "https://asia.nikkei.com/economy/indonesia-cracks-down-on-industrial-tax-cheats-as-fiscal-deficit-widens",
    "snippet": "Gemini unavailable – default relevance.",
    "source": "asia.nikkei.com",
    "time": "2026-01-15T12:52:19.925238+00:00",
    "region": "APJC",
    "severity": 2,
    "type": "PHYSICAL SECURITY"
  },
  {
    "title": "China Vanke proposes fresh 90-day extension on yuan bonds worth $817m",
    "url": "https://asia.nikkei.com/business/markets/china-debt-crunch/china-vanke-proposes-fresh-90-day-extension-on-yuan-bonds-worth-817m",
    "snippet": "Gemini unavailable – default relevance.",
    "source": "asia.nikkei.com",
    "time": "2026-01-15T12:52:19.925207+00:00",
    "region": "APJC",
    "severity": 2,
    "type": "PHYSICAL SECURITY"
  },
  {
    "title": "Supply chain snags and TSMC's big spending",
    "url": "https://asia.nikkei.com/techasia/supply-chain-snags-and-tsmc-s-big-spending",
    "snippet": "Gemini unavailable – default relevance.",
    "source": "asia.nikkei.com",
    "time": "2026-01-15T12:52:19.925176+00:00",
    "region": "Global",
    "severity": 2,
    "type": "PHYSICAL SECURITY"
  },
  {
    "title": "Japan opposition groups to form new party to fight snap election",
    "url": "https://asia.nikkei.com/politics/japan-election/japan-opposition-groups-to-form-new-party-to-fight-snap-election",
    "snippet": "Gemini unavailable – default relevance.",
    "source": "asia.nikkei.com",
    "time": "2026-01-15T12:52:19.925139+00:00",
    "region": "APJC",
    "severity": 2,
    "type": "PHYSICAL SECURITY"
  },
  {
    "title": "Four months into 50% tariff regime, Indian exports to US down just 1%",
    "url": "https://asia.nikkei.com/economy/trade-war/trump-tariffs/four-months-into-50-tariff-regime-indian-exports-to-us-down-just-12",
    "snippet": "Gemini unavailable – default relevance.",
    "source": "asia.nikkei.com",
    "time": "2026-01-15T12:52:19.925093+00:00",
    "region": "APJC",
    "severity": 2,
    "type": "PHYSICAL SECURITY"
  },
  {
    "title": "Hong Kong employee insurance costs to jump 15% amid surge in day surgeries: study",
    "url": "https://www.scmp.com/news/hong-kong/health-environment/article/3340047/hong-kong-employee-insurance-costs-jump-15-amid-surge-day-surgeries-study?utm_source=rss_feed",
    "snippet": "Gemini unavailable – default relevance.",
    "source": "scmp.com",
    "time": "2026-01-15T12:50:44+00:00",
    "region": "Global",
    "severity": 2,
    "type": "PHYSICAL SECURITY"
  },
  {
    "title": "Iran Says Protester Was Not Sentenced to Death After International Outcry",
    "url": "https://www.nytimes.com/2026/01/15/world/middleeast/iran-protests-erfan-soltani-execution.html",
    "snippet": "Gemini unavailable – default relevance.",
    "source": "nytimes.com",
    "time": "2026-01-15T12:50:05+00:00",
    "region": "Global",
    "severity": 2,
    "type": "PHYSICAL SECURITY"
  },
  {
    "title": "Boeing knew of flaw in part linked to UPS plane crash, report says",
    "url": "https://www.bbc.com/news/articles/cly56w0p9e1o?at_medium=RSS&at_campaign=rss",
    "snippet": "Gemini unavailable – default relevance.",
    "source": "bbc.com",
    "time": "2026-01-15T12:49:56+00:00",
    "region": "Global",
    "severity": 2,
    "type": "PHYSICAL SECURITY"
  },
  {
    "title": "Maersk sets the pace for Red Sea return with service reschedule",
    "url": "https://theloadstar.com/maersk-sets-the-pace-for-red-sea-return-with-service-reschedule/",
    "snippet": "Gemini unavailable – default relevance.",
    "source": "theloadstar.com",
    "time": "2026-01-15T12:46:57+00:00",
    "region": "APJC",
    "severity": 2,
    "type": "PHYSICAL SECURITY"
  },
  {
    "title": "California’s FAST Group – last-mile dream becomes bankruptcy nightmare",
    "url": "https://theloadstar.com/californias-fast-group-last-mile-dream-becomes-bankruptcy-nightmare/",
    "snippet": "Gemini unavailable – default relevance.",
    "source": "theloadstar.com",
    "time": "2026-01-15T12:44:17+00:00",
    "region": "APJC",
    "severity": 2,
    "type": "PHYSICAL SECURITY"
  },
  {
    "title": "Kremlin warns Ukraine running out of time to accept peace terms as winter crisis deepens",
    "url": "https://www.scmp.com/news/world/russia-central-asia/article/3340046/kremlin-warns-ukraine-running-out-time-accept-peace-terms-winter-crisis-deepens?utm_source=rss_feed",
    "snippet": "Gemini unavailable – default relevance.",
    "source": "scmp.com",
    "time": "2026-01-15T12:41:49+00:00",
    "region": "EMEA",
    "severity": 2,
    "type": "PHYSICAL SECURITY"
  },
  {
    "title": "Trump to meet Venezuelan opposition leader and Nobel peace laureate Maria Corina Machado later – US politics live",
    "url": "https://www.theguardian.com/us-news/live/2026/jan/15/us-politics-latest-news-updates-donald-trump-venezuela-maria-corina-machado",
    "snippet": "Gemini unavailable – default relevance.",
    "source": "theguardian.com",
    "time": "2026-01-15T12:41:16+00:00",
    "region": "Global",
    "severity": 2,
    "type": "PHYSICAL SECURITY"
  },
  {
    "title": "‘Frustration & despair’ in Gaza as US announces ceasefire phase 2",
    "url": "https://www.aljazeera.com/video/newsfeed/2026/1/15/frustration-despair-in-gaza-as-us-announces-ceasefire-phase-2?traffic_source=rss",
    "snippet": "Gemini unavailable – default relevance.",
    "source": "aljazeera.com",
    "time": "2026-01-15T12:38:49+00:00",
    "region": "EMEA",
    "severity": 2,
    "type": "PHYSICAL SECURITY"
  },
  {
    "title": "The U.S. Is Pressing Mexico to Allow U.S. Forces to Fight Cartels",
    "url": "https://www.nytimes.com/2026/01/15/world/americas/us-mexico-cartels.html",
    "snippet": "Gemini unavailable – default relevance.",
    "source": "nytimes.com",
    "time": "2026-01-15T12:38:23+00:00",
    "region": "AMER",
    "severity": 2,
    "type": "PHYSICAL SECURITY"
  },
  {
    "title": "Kukdong MES eyes global container leasing business as prices slump",
    "url": "https://theloadstar.com/kukdong-mes-eyes-global-container-leasing-business-as-prices-slump/",
    "snippet": "Gemini unavailable – default relevance.",
    "source": "theloadstar.com",
    "time": "2026-01-15T12:37:01+00:00",
    "region": "APJC",
    "severity": 2,
    "type": "PHYSICAL SECURITY"
  },
  {
    "title": "China’s subsidy change adds to EV makers’ stress as more buyers consider petrol cars",
    "url": "https://www.scmp.com/business/china-business/article/3340041/chinas-subsidy-change-adds-ev-makers-stress-more-buyers-consider-petrol-cars?utm_source=rss_feed",
    "snippet": "Gemini unavailable – default relevance.",
    "source": "scmp.com",
    "time": "2026-01-15T12:30:14+00:00",
    "region": "APJC",
    "severity": 2,
    "type": "PHYSICAL SECURITY"
  },
  {
    "title": "An internally split Europe can never fully engage China and Asia",
    "url": "https://www.scmp.com/opinion/world-opinion/article/3339744/internally-split-europe-can-never-fully-engage-china-and-asia?utm_source=rss_feed",
    "snippet": "Gemini unavailable – default relevance.",
    "source": "scmp.com",
    "time": "2026-01-15T12:30:09+00:00",
    "region": "APJC",
    "severity": 2,
    "type": "PHYSICAL SECURITY"
  },
  {
    "title": "Trump targets AI chips with new tariffs – but most imports escape",
    "url": "https://theloadstar.com/trump-targets-ai-chips-with-new-tariffs-but-most-imports-escape/",
    "snippet": "Gemini unavailable – default relevance.",
    "source": "theloadstar.com",
    "time": "2026-01-15T12:29:14+00:00",
    "region": "Global",
    "severity": 2,
    "type": "PHYSICAL SECURITY"
  },
  {
    "title": "UPS MD-11 freighter crash – is the tri-jets era nearing its end?",
    "url": "https://theloadstar.com/ups-md-11-freighter-crash-is-the-tri-jets-era-nearing-its-end/",
    "snippet": "Gemini unavailable – default relevance.",
    "source": "theloadstar.com",
    "time": "2026-01-15T12:28:05+00:00",
    "region": "Global",
    "severity": 2,
    "type": "PHYSICAL SECURITY"
  },
  {
    "title": "Hong Kong police shoot man wielding meat cleaver in Tuen Mun",
    "url": "https://www.scmp.com/news/hong-kong/law-and-crime/article/3340045/police-shoot-man-wielding-meat-cleaver-hong-kongs-tuen-mun?utm_source=rss_feed",
    "snippet": "Gemini unavailable – default relevance.",
    "source": "scmp.com",
    "time": "2026-01-15T12:27:16+00:00",
    "region": "Global",
    "severity": 2,
    "type": "PHYSICAL SECURITY"
  },
  {
    "title": "Gaza’s ceasefire moves to next phase, but is it working?",
    "url": "https://www.aljazeera.com/video/newsfeed/2026/1/15/gazas-ceasefire-moves-to-next-phase-but-is-it-working?traffic_source=rss",
    "snippet": "Gemini unavailable – default relevance.",
    "source": "aljazeera.com",
    "time": "2026-01-15T12:26:24+00:00",
    "region": "EMEA",
    "severity": 2,
    "type": "PHYSICAL SECURITY"
  },
  {
    "title": "‘Squished Between Chairs’ on a Train: How Some Passengers Survived a Crane Collapse",
    "url": "https://www.nytimes.com/2026/01/15/world/asia/thailand-train-crane-survivors.html",
    "snippet": "Gemini unavailable – default relevance.",
    "source": "nytimes.com",
    "time": "2026-01-15T12:20:13+00:00",
    "region": "APJC",
    "severity": 2,
    "type": "PHYSICAL SECURITY"
  },
  {
    "title": "FMT apologises for racial question linking Malaysia’s ‘Chinese Problem’ and Palestine",
    "url": "https://www.scmp.com/news/asia/southeast-asia/article/3340043/fmt-apologises-racial-question-linking-malaysias-chinese-problem-and-palestine?utm_source=rss_feed",
    "snippet": "Gemini unavailable – default relevance.",
    "source": "scmp.com",
    "time": "2026-01-15T12:12:43+00:00",
    "region": "APJC",
    "severity": 2,
    "type": "PHYSICAL SECURITY"
  },
  {
    "title": "Trump on the future of Gaza: In his own words",
    "url": "https://www.aljazeera.com/video/2026/1/15/trump-on-the-future-of-gaza-in-his-own-words?traffic_source=rss",
    "snippet": "Gemini unavailable – default relevance.",
    "source": "aljazeera.com",
    "time": "2026-01-15T12:08:02+00:00",
    "region": "EMEA",
    "severity": 2,
    "type": "PHYSICAL SECURITY"
  },
  {
    "title": "Iran reopens airspace after Trump says protest crackdown has eased",
    "url": "https://www.washingtonpost.com/world/2026/01/15/us-iran-trump-military-strike-airspace/",
    "snippet": "Gemini unavailable – default relevance.",
    "source": "washingtonpost.com",
    "time": "2026-01-15T12:07:38+00:00",
    "region": "Global",
    "severity": 2,
    "type": "PHYSICAL SECURITY"
  },
  {
    "title": "Ofwat launches investigation into South East Water",
    "url": "https://www.bbc.com/news/articles/cq6vm1rp2pjo?at_medium=RSS&at_campaign=rss",
    "snippet": "Gemini unavailable – default relevance.",
    "source": "bbc.com",
    "time": "2026-01-15T12:05:47+00:00",
    "region": "AMER",
    "severity": 2,
    "type": "PHYSICAL SECURITY"
  },
  {
    "title": "‘Follow the flow’ – don’t trust AI and admire Danish M&A",
    "url": "https://theloadstar.com/follow-the-flow-dont-trust-ai-and-admire-danish-ma/",
    "snippet": "Gemini unavailable – default relevance.",
    "source": "theloadstar.com",
    "time": "2026-01-15T12:03:10+00:00",
    "region": "Global",
    "severity": 2,
    "type": "PHYSICAL SECURITY"
  },
  {
    "title": "Voting in Uganda’s general election delayed by technical and logistical issues",
    "url": "https://www.theguardian.com/world/2026/jan/15/uganda-vote-election-yoweri-museveni-bobi-wine",
    "snippet": "Gemini unavailable – default relevance.",
    "source": "theguardian.com",
    "time": "2026-01-15T12:02:38+00:00",
    "region": "Global",
    "severity": 2,
    "type": "PHYSICAL SECURITY"
  },
  {
    "title": "Israel carries out raids and demolitions, arrests dozens across West Bank",
    "url": "https://www.aljazeera.com/news/2026/1/15/israel-carries-out-raids-and-demolitions-arrests-dozens-across-west-bank?traffic_source=rss",
    "snippet": "Gemini unavailable – default relevance.",
    "source": "aljazeera.com",
    "time": "2026-01-15T12:00:57+00:00",
    "region": "EMEA",
    "severity": 2,
    "type": "PHYSICAL SECURITY"
  },
  {
    "title": "Stalled work to resume as Hong Kong distributes 3,000 fire-tested scaffold nets",
    "url": "https://www.scmp.com/news/hong-kong/society/article/3340040/stalled-work-resume-hong-kong-distributes-3000-fire-tested-scaffold-nets?utm_source=rss_feed",
    "snippet": "Gemini unavailable – default relevance.",
    "source": "scmp.com",
    "time": "2026-01-15T12:00:53+00:00",
    "region": "Global",
    "severity": 2,
    "type": "PHYSICAL SECURITY"
  },
  {
    "title": "New York bakery staff push for union, claiming they were forced to bake for Israeli fundraisers",
    "url": "https://www.theguardian.com/business/2026/jan/15/new-york-bakery-union-israel",
    "snippet": "Gemini unavailable – default relevance.",
    "source": "theguardian.com",
    "time": "2026-01-15T12:00:18+00:00",
    "region": "EMEA",
    "severity": 2,
    "type": "PHYSICAL SECURITY"
  },
  {
    "title": "Green forest fire notification in Sudan",
    "url": "https://www.gdacs.org/report.aspx?eventtype=WF&eventid=1026940",
    "snippet": "Gemini unavailable – default relevance.",
    "source": "gdacs.org",
    "time": "2026-01-15T12:00:18+00:00",
    "region": "Global",
    "severity": 2,
    "type": "PHYSICAL SECURITY"
  },
  {
    "title": "Green forest fire notification in Australia",
    "url": "https://www.gdacs.org/report.aspx?eventtype=WF&eventid=1026953",
    "snippet": "Gemini unavailable – default relevance.",
    "source": "gdacs.org",
    "time": "2026-01-15T12:00:10+00:00",
    "region": "APJC",
    "severity": 2,
    "type": "PHYSICAL SECURITY"
  },
  {
    "title": "China targets wealthy influencers with audits, fines as fiscal pressures rise",
    "url": "https://www.scmp.com/economy/china-economy/article/3340007/china-targets-wealthy-influencers-audits-fines-fiscal-pressures-rise?utm_source=rss_feed",
    "snippet": "Gemini unavailable – default relevance.",
    "source": "scmp.com",
    "time": "2026-01-15T12:00:09+00:00",
    "region": "APJC",
    "severity": 2,
    "type": "PHYSICAL SECURITY"
  },
  {
    "title": "Shanghai and Singapore still busiest box ports – but hit ‘complexity ceiling’",
    "url": "https://theloadstar.com/shanghai-and-singapore-still-the-worlds-busiest-box-ports/",
    "snippet": "Gemini unavailable – default relevance.",
    "source": "theloadstar.com",
    "time": "2026-01-15T11:59:48+00:00",
    "region": "APJC",
    "severity": 2,
    "type": "PHYSICAL SECURITY"
  },
  {
    "title": "Israel uses Somaliland to make it “seen as a regional power”",
    "url": "https://www.aljazeera.com/video/quotable/2026/1/15/israel-uses-somaliland-to-make-it-seen-as-a-regional?traffic_source=rss",
    "snippet": "Gemini unavailable – default relevance.",
    "source": "aljazeera.com",
    "time": "2026-01-15T11:59:00+00:00",
    "region": "EMEA",
    "severity": 2,
    "type": "PHYSICAL SECURITY"
  },
  {
    "title": "Nie Weiping, Chinese Go master known for dramatic victory over Japanese rival, dies at 73",
    "url": "https://www.scmp.com/news/china/politics/article/3340042/nie-weiping-chinese-go-master-known-dramatic-victory-over-japanese-rival-dies-73?utm_source=rss_feed",
    "snippet": "Gemini unavailable – default relevance.",
    "source": "scmp.com",
    "time": "2026-01-15T11:57:06+00:00",
    "region": "APJC",
    "severity": 2,
    "type": "PHYSICAL SECURITY"
  },
  {
    "title": "How Chinese corruption busters are tracking down bribes paid in cryptocurrency",
    "url": "https://www.scmp.com/news/china/politics/article/3340038/how-chinese-corruption-busters-are-tracking-down-bribes-paid-cryptocurrency?utm_source=rss_feed",
    "snippet": "Gemini unavailable – default relevance.",
    "source": "scmp.com",
    "time": "2026-01-15T11:51:31+00:00",
    "region": "APJC",
    "severity": 2,
    "type": "PHYSICAL SECURITY"
  },
  {
    "title": "Maersk heads back to the Red Sea",
    "url": "https://splash247.com/maersk-heads-back-to-the-red-sea/",
    "snippet": "Gemini unavailable – default relevance.",
    "source": "splash247.com",
    "time": "2026-01-15T11:50:51+00:00",
    "region": "APJC",
    "severity": 2,
    "type": "PHYSICAL SECURITY"
  },
  {
    "title": "Investors line up bids as Santos Tecon 10 terminal gets green light",
    "url": "https://theloadstar.com/investors-line-up-bids-as-santos-tecon-10-terminal-gets-green-light/",
    "snippet": "Gemini unavailable – default relevance.",
    "source": "theloadstar.com",
    "time": "2026-01-15T11:48:43+00:00",
    "region": "AMER",
    "severity": 2,
    "type": "PHYSICAL SECURITY"
  },
  {
    "title": "Ecommerce share of air cargo traffic still growing as capacity rebounds",
    "url": "https://theloadstar.com/ecommerce-share-of-air-cargo-traffic-still-growing-as-capacity-rebounds/",
    "snippet": "Gemini unavailable – default relevance.",
    "source": "theloadstar.com",
    "time": "2026-01-15T11:34:08+00:00",
    "region": "Global",
    "severity": 2,
    "type": "PHYSICAL SECURITY"
  },
  {
    "title": "Widespread delays hit Uganda election amid internet shutdown",
    "url": "https://www.bbc.com/news/articles/cx2xn1yvgr4o?at_medium=RSS&at_campaign=rss",
    "snippet": "Gemini unavailable – default relevance.",
    "source": "bbc.com",
    "time": "2026-01-15T11:33:53+00:00",
    "region": "Global",
    "severity": 2,
    "type": "PHYSICAL SECURITY"
  },
  {
    "title": "Nearly 5 Million Accounts Removed Under Australia’s New Social Media Ban",
    "url": "https://www.nytimes.com/2026/01/15/world/australia/social-media-ban-australia.html",
    "snippet": "Gemini unavailable – default relevance.",
    "source": "nytimes.com",
    "time": "2026-01-15T11:31:05+00:00",
    "region": "APJC",
    "severity": 2,
    "type": "PHYSICAL SECURITY"
  },
  {
    "title": "UK economy grew by 0.3% in November, beating forecasts",
    "url": "https://www.bbc.com/news/articles/c8d041pp85mo?at_medium=RSS&at_campaign=rss",
    "snippet": "Gemini unavailable – default relevance.",
    "source": "bbc.com",
    "time": "2026-01-15T11:16:47+00:00",
    "region": "EMEA",
    "severity": 2,
    "type": "PHYSICAL SECURITY"
  },
  {
    "title": "Trump to discuss Venezuela’s future with Machado after Maduro’s capture",
    "url": "https://www.theguardian.com/us-news/2026/jan/15/trump-maria-corina-machado-venezuela",
    "snippet": "Gemini unavailable – default relevance.",
    "source": "theguardian.com",
    "time": "2026-01-15T11:07:26+00:00",
    "region": "Global",
    "severity": 2,
    "type": "PHYSICAL SECURITY"
  },
  {
    "title": "ICE officer shoots Venezuelan immigrant in Minneapolis: What we know",
    "url": "https://www.aljazeera.com/news/2026/1/15/ice-officer-shoots-venezuelan-immigrant-in-minneapolis-what-we-know?traffic_source=rss",
    "snippet": "Gemini unavailable – default relevance.",
    "source": "aljazeera.com",
    "time": "2026-01-15T11:06:02+00:00",
    "region": "Global",
    "severity": 2,
    "type": "PHYSICAL SECURITY"
  },
  {
    "title": "Who is Nickolay Mladenov, the diplomat tasked with ‘disarming Gaza’?",
    "url": "https://www.aljazeera.com/features/2026/1/15/who-is-nickolay-mladenov-the-diplomat-tasked-with-disarming-gaza?traffic_source=rss",
    "snippet": "Gemini unavailable – default relevance.",
    "source": "aljazeera.com",
    "time": "2026-01-15T11:01:00+00:00",
    "region": "EMEA",
    "severity": 2,
    "type": "PHYSICAL SECURITY"
  },
  {
    "title": "Why big oil giants may not rush to buy into Donald Trump’s Venezuelan vision",
    "url": "https://www.theguardian.com/business/2026/jan/15/trump-big-oil-venezuela",
    "snippet": "Gemini unavailable – default relevance.",
    "source": "theguardian.com",
    "time": "2026-01-15T11:00:03+00:00",
    "region": "AMER",
    "severity": 2,
    "type": "PHYSICAL SECURITY"
  },
  {
    "title": "Trump’s promised manufacturing boom is a bust so far",
    "url": "https://www.washingtonpost.com/business/2026/01/15/trump-manufacturing-jobs-tariffs/",
    "snippet": "Gemini unavailable – default relevance.",
    "source": "washingtonpost.com",
    "time": "2026-01-15T11:00:00+00:00",
    "region": "Global",
    "severity": 2,
    "type": "PHYSICAL SECURITY"
  },
  {
    "title": "4 Outdated Habits Destroying Your SOC's MTTR in 2026",
    "url": "https://thehackernews.com/2026/01/4-outdated-habits-destroying-your-socs.html",
    "snippet": "Gemini unavailable – default relevance.",
    "source": "thehackernews.com",
    "time": "2026-01-15T11:00:00+00:00",
    "region": "Global",
    "severity": 2,
    "type": "PHYSICAL SECURITY"
  },
  {
    "title": "Russia Knocks Out the Heat in Ukraine",
    "url": "https://www.nytimes.com/2026/01/15/world/europe/ukraine-kyiv-winter-heating-power-outages.html",
    "snippet": "Gemini unavailable – default relevance.",
    "source": "nytimes.com",
    "time": "2026-01-15T10:52:49+00:00",
    "region": "EMEA",
    "severity": 2,
    "type": "PHYSICAL SECURITY"
  },
  {
    "title": "Lebanese fear US has given green light for Israeli escalation",
    "url": "https://www.aljazeera.com/features/2026/1/15/lebanese-fear-us-has-given-green-light-for-israeli-escalation?traffic_source=rss",
    "snippet": "Gemini unavailable – default relevance.",
    "source": "aljazeera.com",
    "time": "2026-01-15T10:46:18+00:00",
    "region": "EMEA",
    "severity": 2,
    "type": "PHYSICAL SECURITY"
  },
  {
    "title": "Zelensky declares energy emergency as biting cold persists",
    "url": "https://www.bbc.com/news/articles/cq6vm677z76o?at_medium=RSS&at_campaign=rss",
    "snippet": "Gemini unavailable – default relevance.",
    "source": "bbc.com",
    "time": "2026-01-15T10:41:04+00:00",
    "region": "EMEA",
    "severity": 2,
    "type": "PHYSICAL SECURITY"
  },
  {
    "title": "EU-Latin America trade deal: Who wins?",
    "url": "https://www.aljazeera.com/video/counting-the-cost/2026/1/15/eu-latin-america-trade-deal-who-wins-2?traffic_source=rss",
    "snippet": "Gemini unavailable – default relevance.",
    "source": "aljazeera.com",
    "time": "2026-01-15T10:35:51+00:00",
    "region": "AMER",
    "severity": 2,
    "type": "PHYSICAL SECURITY"
  },
  {
    "title": "Fredriksen goes back to Hengli for two more VLCCs",
    "url": "https://splash247.com/fredriksen-goes-back-to-hengli-for-two-more-vlccs/",
    "snippet": "Gemini unavailable – default relevance.",
    "source": "splash247.com",
    "time": "2026-01-15T10:35:00+00:00",
    "region": "APJC",
    "severity": 2,
    "type": "PHYSICAL SECURITY"
  },
  {
    "title": "Was Nicolas Maduro ‘flooding’ the US with fentanyl, as White House claims?",
    "url": "https://www.aljazeera.com/features/2026/1/15/was-nicolas-maduro-flooding-the-us-with-fentanyl-as-white-house-claims?traffic_source=rss",
    "snippet": "Gemini unavailable – default relevance.",
    "source": "aljazeera.com",
    "time": "2026-01-15T10:27:53+00:00",
    "region": "Global",
    "severity": 2,
    "type": "PHYSICAL SECURITY"
  },
  {
    "title": "Federal agent shoots Minneapolis man in leg after shovel attack, officials say",
    "url": "https://www.bbc.com/news/articles/c205677pxvxo?at_medium=RSS&at_campaign=rss",
    "snippet": "Gemini unavailable – default relevance.",
    "source": "bbc.com",
    "time": "2026-01-15T10:22:45+00:00",
    "region": "Global",
    "severity": 2,
    "type": "PHYSICAL SECURITY"
  },
  {
    "title": "X to stop Grok AI from undressing images of real people after backlash",
    "url": "https://www.bbc.com/news/articles/ce8gz8g2qnlo?at_medium=RSS&at_campaign=rss",
    "snippet": "Gemini unavailable – default relevance.",
    "source": "bbc.com",
    "time": "2026-01-15T10:18:56+00:00",
    "region": "Global",
    "severity": 2,
    "type": "PHYSICAL SECURITY"
  },
  {
    "title": "Nobel Committee Takes Heat at Home as Machado Courts Trump in D.C.",
    "url": "https://www.nytimes.com/2026/01/15/world/americas/machado-trump-meeting-nobel-peace-prize.html",
    "snippet": "Gemini unavailable – default relevance.",
    "source": "nytimes.com",
    "time": "2026-01-15T10:03:49+00:00",
    "region": "Global",
    "severity": 2,
    "type": "PHYSICAL SECURITY"
  },
  {
    "title": "Trump Vows to Make Venezuela Rich. It Will Take More Than U.S. Cash.",
    "url": "https://www.nytimes.com/2026/01/15/business/venezuela-oil-history-investment.html",
    "snippet": "Gemini unavailable – default relevance.",
    "source": "nytimes.com",
    "time": "2026-01-15T10:02:43+00:00",
    "region": "Global",
    "severity": 2,
    "type": "PHYSICAL SECURITY"
  },
  {
    "title": "Leading Prediction Firms Share a Commonality: Donald Trump Jr.",
    "url": "https://www.nytimes.com/2026/01/15/us/politics/donald-trump-jr-prediction-markets.html",
    "snippet": "Gemini unavailable – default relevance.",
    "source": "nytimes.com",
    "time": "2026-01-15T10:02:18+00:00",
    "region": "Global",
    "severity": 2,
    "type": "PHYSICAL SECURITY"
  },
  {
    "title": "Venezuela Strongman and Maduro Ally, Diosdado Cabello, Faces an Uneasy Transition",
    "url": "https://www.nytimes.com/2026/01/15/world/americas/venezuela-diosdado-cabello-maduro.html",
    "snippet": "Gemini unavailable – default relevance.",
    "source": "nytimes.com",
    "time": "2026-01-15T10:00:51+00:00",
    "region": "AMER",
    "severity": 2,
    "type": "PHYSICAL SECURITY"
  },
  {
    "title": "With smiling selfies and K-pop jam session, Japan and China woo South Korea",
    "url": "https://www.washingtonpost.com/world/2026/01/15/china-japan-south-korea-relations/",
    "snippet": "Gemini unavailable – default relevance.",
    "source": "washingtonpost.com",
    "time": "2026-01-15T10:00:40+00:00",
    "region": "APJC",
    "severity": 2,
    "type": "PHYSICAL SECURITY"
  },
  {
    "title": "The other effort to control the Fed",
    "url": "https://www.washingtonpost.com/business/2026/01/15/other-effort-control-fed/",
    "snippet": "Gemini unavailable – default relevance.",
    "source": "washingtonpost.com",
    "time": "2026-01-15T10:00:30+00:00",
    "region": "AMER",
    "severity": 2,
    "type": "PHYSICAL SECURITY"
  },
  {
    "title": "‘The consumers are still out there’: why a bankruptcy for Saks Global may not spell the end",
    "url": "https://www.theguardian.com/business/2026/jan/15/saks-global-bankruptcy",
    "snippet": "Gemini unavailable – default relevance.",
    "source": "theguardian.com",
    "time": "2026-01-15T10:00:02+00:00",
    "region": "Global",
    "severity": 2,
    "type": "PHYSICAL SECURITY"
  },
  {
    "title": "Iran’s protests come after waves of unrest, spanning years",
    "url": "https://www.washingtonpost.com/world/2026/01/15/iran-protests-history-death-toll/",
    "snippet": "Gemini unavailable – default relevance.",
    "source": "washingtonpost.com",
    "time": "2026-01-15T10:00:00+00:00",
    "region": "Global",
    "severity": 2,
    "type": "PHYSICAL SECURITY"
  },
  {
    "title": "Why more seniors are being asked to care for their partners — alone",
    "url": "https://www.washingtonpost.com/health/2026/01/10/senior-caregivers-spouse/",
    "snippet": "Gemini unavailable – default relevance.",
    "source": "washingtonpost.com",
    "time": "2026-01-15T10:00:00+00:00",
    "region": "Global",
    "severity": 2,
    "type": "PHYSICAL SECURITY"
  },
  {
    "title": "Equinor taps Archer for deepwater P&A work in Gulf of Mexico",
    "url": "https://splash247.com/equinor-taps-archer-for-deepwater-pa-work-in-gulf-of-mexico/",
    "snippet": "Gemini unavailable – default relevance.",
    "source": "splash247.com",
    "time": "2026-01-15T10:00:00+00:00",
    "region": "AMER",
    "severity": 2,
    "type": "PHYSICAL SECURITY"
  },
  {
    "title": "FTC bans GM from selling drivers' location data for five years",
    "url": "https://www.bleepingcomputer.com/news/security/ftc-bans-general-motors-from-selling-drivers-location-data-for-five-years/",
    "snippet": "Gemini unavailable – default relevance.",
    "source": "bleepingcomputer.com",
    "time": "2026-01-15T09:59:30+00:00",
    "region": "Global",
    "severity": 2,
    "type": "PHYSICAL SECURITY"
  },
  {
    "title": "Microsoft Legal Action Disrupts RedVDS Cybercrime Infrastructure Used for Online Fraud",
    "url": "https://thehackernews.com/2026/01/microsoft-legal-action-disrupts-redvds.html",
    "snippet": "Gemini unavailable – default relevance.",
    "source": "thehackernews.com",
    "time": "2026-01-15T09:37:00+00:00",
    "region": "Global",
    "severity": 2,
    "type": "PHYSICAL SECURITY"
  },
  {
    "title": "Watch: Aerial footage shows cars swept away by flash floods in Australia",
    "url": "https://www.bbc.com/news/videos/c1wz807vpglo?at_medium=RSS&at_campaign=rss",
    "snippet": "Gemini unavailable – default relevance.",
    "source": "bbc.com",
    "time": "2026-01-15T09:30:56+00:00",
    "region": "APJC",
    "severity": 2,
    "type": "PHYSICAL SECURITY"
  },
  {
    "title": "Thailand Has 2nd Deadly Incident Involving a Crane in 2 Days",
    "url": "https://www.nytimes.com/2026/01/15/world/asia/thailand-crane-expressway-rama2.html",
    "snippet": "Gemini unavailable – default relevance.",
    "source": "nytimes.com",
    "time": "2026-01-15T09:11:05+00:00",
    "region": "APJC",
    "severity": 2,
    "type": "PHYSICAL SECURITY"
  },
  {
    "title": "Palo Alto Networks warns of DoS bug letting hackers disable firewalls",
    "url": "https://www.bleepingcomputer.com/news/security/palo-alto-networks-warns-of-dos-bug-letting-hackers-disable-firewalls/",
    "snippet": "Gemini unavailable – default relevance.",
    "source": "bleepingcomputer.com",
    "time": "2026-01-15T09:02:42+00:00",
    "region": "Global",
    "severity": 2,
    "type": "PHYSICAL SECURITY"
  },
  {
    "title": "Singapore's opposition leader stripped of title after conviction for lying",
    "url": "https://www.bbc.com/news/articles/cp80217r1kpo?at_medium=RSS&at_campaign=rss",
    "snippet": "Gemini unavailable – default relevance.",
    "source": "bbc.com",
    "time": "2026-01-15T08:59:23+00:00",
    "region": "APJC",
    "severity": 2,
    "type": "PHYSICAL SECURITY"
  },
  {
    "title": "Green earthquake (Magnitude 5.9M, Depth:41.324km) in United States 15/01/2026 08:52 UTC, Few people affected in MMI III.",
    "url": "https://www.gdacs.org/report.aspx?eventtype=EQ&eventid=1519597",
    "snippet": "Gemini unavailable – default relevance.",
    "source": "gdacs.org",
    "time": "2026-01-15T08:58:13+00:00",
    "region": "AMER",
    "severity": 2,
    "type": "PHYSICAL SECURITY"
  },
  {
    "title": "Bulkers ride China’s bauxite surge",
    "url": "https://splash247.com/bulkers-ride-chinas-bauxite-surge/",
    "snippet": "Gemini unavailable – default relevance.",
    "source": "splash247.com",
    "time": "2026-01-15T08:44:53+00:00",
    "region": "APJC",
    "severity": 2,
    "type": "PHYSICAL SECURITY"
  },
  {
    "title": "Geneva Dry continues to add leading commodity and shipping speakers",
    "url": "https://splash247.com/geneva-dry-continues-to-add-leading-commodity-and-shipping-speakers/",
    "snippet": "Gemini unavailable – default relevance.",
    "source": "splash247.com",
    "time": "2026-01-15T08:24:39+00:00",
    "region": "APJC",
    "severity": 2,
    "type": "PHYSICAL SECURITY"
  },
  {
    "title": "Palo Alto Fixes GlobalProtect DoS Flaw That Can Crash Firewalls Without Login",
    "url": "https://thehackernews.com/2026/01/palo-alto-fixes-globalprotect-dos-flaw.html",
    "snippet": "Gemini unavailable – default relevance.",
    "source": "thehackernews.com",
    "time": "2026-01-15T08:18:00+00:00",
    "region": "Global",
    "severity": 2,
    "type": "PHYSICAL SECURITY"
  },
  {
    "title": "Shipping awaits outcome of Iran-Trump standoff",
    "url": "https://splash247.com/shipping-awaits-outcome-of-iran-trump-standoff/",
    "snippet": "Gemini unavailable – default relevance.",
    "source": "splash247.com",
    "time": "2026-01-15T08:00:51+00:00",
    "region": "EMEA",
    "severity": 2,
    "type": "PHYSICAL SECURITY"
  },
  {
    "title": "Green flood alert in Peru",
    "url": "https://www.gdacs.org/report.aspx?eventtype=FL&eventid=1103713",
    "snippet": "Gemini unavailable – default relevance.",
    "source": "gdacs.org",
    "time": "2026-01-15T07:45:24+00:00",
    "region": "AMER",
    "severity": 2,
    "type": "PHYSICAL SECURITY"
  },
  {
    "title": "Yangzijiang Maritime ramps up asset push with 16-ship newbuild spree",
    "url": "https://splash247.com/yangzijiang-maritime-ramps-up-asset-push-with-16-ship-newbuild-spree/",
    "snippet": "Gemini unavailable – default relevance.",
    "source": "splash247.com",
    "time": "2026-01-15T07:30:44+00:00",
    "region": "APJC",
    "severity": 2,
    "type": "PHYSICAL SECURITY"
  },
  {
    "title": "Microsoft disrupts massive RedVDS cybercrime virtual desktop service",
    "url": "https://www.bleepingcomputer.com/news/security/microsoft-seizes-servers-disrupts-massive-redvds-cybercrime-platform/",
    "snippet": "Gemini unavailable – default relevance.",
    "source": "bleepingcomputer.com",
    "time": "2026-01-15T07:11:45+00:00",
    "region": "AMER",
    "severity": 2,
    "type": "PHYSICAL SECURITY"
  },
  {
    "title": "Bahri and Hadeed explore iron ore shipping partnership",
    "url": "https://splash247.com/bahri-and-hadeed-explore-iron-ore-shipping-partnership/",
    "snippet": "Gemini unavailable – default relevance.",
    "source": "splash247.com",
    "time": "2026-01-15T07:00:54+00:00",
    "region": "Global",
    "severity": 2,
    "type": "PHYSICAL SECURITY"
  },
  {
    "title": "'It was terrifying': Residents describe carnage after Thai train crash kills 32",
    "url": "https://www.bbc.com/news/articles/cm2yvnen1qyo?at_medium=RSS&at_campaign=rss",
    "snippet": "Gemini unavailable – default relevance.",
    "source": "bbc.com",
    "time": "2026-01-15T06:46:02+00:00",
    "region": "Global",
    "severity": 2,
    "type": "PHYSICAL SECURITY"
  },
  {
    "title": "14 crew rescued from troubled Iranian vessel in the Caspian",
    "url": "https://splash247.com/14-crew-rescued-from-troubled-iranian-vessel-in-the-caspian/",
    "snippet": "Gemini unavailable – default relevance.",
    "source": "splash247.com",
    "time": "2026-01-15T06:30:52+00:00",
    "region": "Global",
    "severity": 2,
    "type": "PHYSICAL SECURITY"
  },
  {
    "title": "'We don't need a sticking plaster', say pub owners",
    "url": "https://www.bbc.com/news/articles/cdexz5rwz55o?at_medium=RSS&at_campaign=rss",
    "snippet": "Gemini unavailable – default relevance.",
    "source": "bbc.com",
    "time": "2026-01-15T06:14:03+00:00",
    "region": "Global",
    "severity": 2,
    "type": "PHYSICAL SECURITY"
  },
  {
    "title": "Rift at top of the Taliban: BBC reveals clash of wills behind internet shutdown",
    "url": "https://www.bbc.com/news/articles/cg7vdpy1l2vo?at_medium=RSS&at_campaign=rss",
    "snippet": "Gemini unavailable – default relevance.",
    "source": "bbc.com",
    "time": "2026-01-15T06:05:57+00:00",
    "region": "Global",
    "severity": 2,
    "type": "PHYSICAL SECURITY"
  },
  {
    "title": "Asyad Shipping steps up VLCC expansion with fresh Hanwha Ocean order",
    "url": "https://splash247.com/asyad-shipping-steps-up-vlcc-expansion-with-fresh-hanwha-ocean-order/",
    "snippet": "Gemini unavailable – default relevance.",
    "source": "splash247.com",
    "time": "2026-01-15T06:00:36+00:00",
    "region": "APJC",
    "severity": 2,
    "type": "PHYSICAL SECURITY"
  },
  {
    "title": "Labubu toy manufacturer exploited workers, labour group claims",
    "url": "https://www.bbc.com/news/articles/cn4037v0w12o?at_medium=RSS&at_campaign=rss",
    "snippet": "Gemini unavailable – default relevance.",
    "source": "bbc.com",
    "time": "2026-01-15T05:36:45+00:00",
    "region": "Global",
    "severity": 2,
    "type": "PHYSICAL SECURITY"
  },
  {
    "title": "Trump told 'killing has stopped' in Iran after violent protest crackdown",
    "url": "https://www.bbc.com/news/articles/c07xpndjdd8o?at_medium=RSS&at_campaign=rss",
    "snippet": "Gemini unavailable – default relevance.",
    "source": "bbc.com",
    "time": "2026-01-15T04:57:26+00:00",
    "region": "Global",
    "severity": 2,
    "type": "PHYSICAL SECURITY"
  },
  {
    "title": "Verizon Outage Cuts Off Tens of Thousands of Users",
    "url": "https://www.nytimes.com/2026/01/14/business/verizon-outage-downdetector.html",
    "snippet": "Gemini unavailable – default relevance.",
    "source": "nytimes.com",
    "time": "2026-01-15T03:50:17+00:00",
    "region": "AMER",
    "severity": 2,
    "type": "PHYSICAL SECURITY"
  },
  {
    "title": "ChatGPT's upcoming cross-platform feature is codenamed \"Agora\"",
    "url": "https://www.bleepingcomputer.com/news/artificial-intelligence/chatgpts-upcoming-cross-platform-feature-is-codenamed-agora/",
    "snippet": "Gemini unavailable – default relevance.",
    "source": "bleepingcomputer.com",
    "time": "2026-01-15T03:00:00+00:00",
    "region": "Global",
    "severity": 2,
    "type": "PHYSICAL SECURITY"
  },
  {
    "title": "Denmark warns of 'fundamental disagreement' after White House talks on Greenland",
    "url": "https://www.bbc.com/news/articles/cx20vzz0g8vo?at_medium=RSS&at_campaign=rss",
    "snippet": "Gemini unavailable – default relevance.",
    "source": "bbc.com",
    "time": "2026-01-15T02:56:22+00:00",
    "region": "Global",
    "severity": 2,
    "type": "PHYSICAL SECURITY"
  },
  {
    "title": "Lebanon 13 January 2026",
    "url": "https://www.crisisgroup.org/content/lebanon-13-january-2026",
    "snippet": "Gemini unavailable – default relevance.",
    "source": "crisisgroup.org",
    "time": "2026-01-15T02:42:43+00:00",
    "region": "EMEA",
    "severity": 2,
    "type": "PHYSICAL SECURITY"
  },
  {
    "title": "Saada 14 January 2026",
    "url": "https://www.crisisgroup.org/content/saada-14-january-2026",
    "snippet": "Gemini unavailable – default relevance.",
    "source": "crisisgroup.org",
    "time": "2026-01-15T02:40:22+00:00",
    "region": "Global",
    "severity": 2,
    "type": "PHYSICAL SECURITY"
  },
  {
    "title": "Yemen 14 January 2026",
    "url": "https://www.crisisgroup.org/content/yemen-14-january-2026",
    "snippet": "Gemini unavailable – default relevance.",
    "source": "crisisgroup.org",
    "time": "2026-01-15T02:38:26+00:00",
    "region": "Global",
    "severity": 2,
    "type": "PHYSICAL SECURITY"
  },
  {
    "title": "Washington 14 January 2026",
    "url": "https://www.crisisgroup.org/content/washington-14-january-2026",
    "snippet": "Gemini unavailable – default relevance.",
    "source": "crisisgroup.org",
    "time": "2026-01-15T02:36:09+00:00",
    "region": "Global",
    "severity": 2,
    "type": "PHYSICAL SECURITY"
  },
  {
    "title": "Tehran 14 January 2026",
    "url": "https://www.crisisgroup.org/content/tehran-14-january-2026",
    "snippet": "Gemini unavailable – default relevance.",
    "source": "crisisgroup.org",
    "time": "2026-01-15T02:34:43+00:00",
    "region": "EMEA",
    "severity": 2,
    "type": "PHYSICAL SECURITY"
  },
  {
    "title": "Lebanon 14 January 2026",
    "url": "https://www.crisisgroup.org/content/lebanon-14-january-2026",
    "snippet": "Gemini unavailable – default relevance.",
    "source": "crisisgroup.org",
    "time": "2026-01-15T02:33:23+00:00",
    "region": "EMEA",
    "severity": 2,
    "type": "PHYSICAL SECURITY"
  },
  {
    "title": "Trump Imposes Limited Tariffs on Foreign Semiconductors",
    "url": "https://www.nytimes.com/2026/01/14/business/economy/trump-chips-tariffs.html",
    "snippet": "Gemini unavailable – default relevance.",
    "source": "nytimes.com",
    "time": "2026-01-15T02:06:58+00:00",
    "region": "Global",
    "severity": 2,
    "type": "PHYSICAL SECURITY"
  },
  {
    "title": "Google plans to make Chrome for Android an agentic browser with Gemini",
    "url": "https://www.bleepingcomputer.com/news/artificial-intelligence/google-plans-to-make-chrome-for-android-an-agentic-browser-with-gemini/",
    "snippet": "Gemini unavailable – default relevance.",
    "source": "bleepingcomputer.com",
    "time": "2026-01-15T01:30:00+00:00",
    "region": "Global",
    "severity": 2,
    "type": "PHYSICAL SECURITY"
  },
  {
    "title": "Iranians abroad wait for news from loved ones amid communications blackout",
    "url": "https://www.washingtonpost.com/world/2026/01/14/iran-blackout-families-contact-protests/",
    "snippet": "Gemini unavailable – default relevance.",
    "source": "washingtonpost.com",
    "time": "2026-01-15T01:15:22+00:00",
    "region": "Global",
    "severity": 2,
    "type": "PHYSICAL SECURITY"
  },
  {
    "title": "U.S. announces launch of second phase of Gaza peace plan",
    "url": "https://www.washingtonpost.com/national-security/2026/01/14/phase-2-gaza-peace-plan-trump/",
    "snippet": "Gemini unavailable – default relevance.",
    "source": "washingtonpost.com",
    "time": "2026-01-15T01:08:31+00:00",
    "region": "EMEA",
    "severity": 2,
    "type": "PHYSICAL SECURITY"
  },
  {
    "title": "Senate blocks Venezuela war powers bill after Vance breaks deadlock",
    "url": "https://www.washingtonpost.com/national-security/2026/01/14/senate-venezuela-war-powers/",
    "snippet": "Gemini unavailable – default relevance.",
    "source": "washingtonpost.com",
    "time": "2026-01-15T00:18:35+00:00",
    "region": "Global",
    "severity": 2,
    "type": "PHYSICAL SECURITY"
  },
  {
    "title": "Google's Personal Intelligence links Gmail, Photos and Search to Gemini",
    "url": "https://www.bleepingcomputer.com/news/artificial-intelligence/googles-personal-intelligence-links-gmail-photos-and-search-to-gemini/",
    "snippet": "Gemini unavailable – default relevance.",
    "source": "bleepingcomputer.com",
    "time": "2026-01-15T00:00:00+00:00",
    "region": "Global",
    "severity": 2,
    "type": "PHYSICAL SECURITY"
  },
  {
    "title": "Why Banks Are So Worried About a 10% Credit Card Rate Cap",
    "url": "https://www.nytimes.com/2026/01/14/business/trump-credit-card-interest-rate-cap-banks.html",
    "snippet": "Gemini unavailable – default relevance.",
    "source": "nytimes.com",
    "time": "2026-01-14T23:39:59+00:00",
    "region": "Global",
    "severity": 2,
    "type": "PHYSICAL SECURITY"
  },
  {
    "title": "DOT to use AI to go after illegal truckers",
    "url": "https://www.freightwaves.com/news/dot-to-use-ai-to-go-after-illegal-truckers",
    "snippet": "Gemini unavailable – default relevance.",
    "source": "freightwaves.com",
    "time": "2026-01-14T23:38:11+00:00",
    "region": "AMER",
    "severity": 2,
    "type": "PHYSICAL SECURITY"
  },
  {
    "title": "ONE Henry Hudson Cargo Operations Resume at Port of Los Angeles After Fire",
    "url": "https://gcaptain.com/one-henry-hudson-cargo-operations-resume-at-port-of-los-angeles-after-fire/",
    "snippet": "Gemini unavailable – default relevance.",
    "source": "gcaptain.com",
    "time": "2026-01-14T23:23:01+00:00",
    "region": "Global",
    "severity": 2,
    "type": "PHYSICAL SECURITY"
  },
  {
    "title": "Bilt Launches New Credit Cards With Mortgage and Rent Rewards: What to Know",
    "url": "https://www.nytimes.com/2026/01/14/business/bilt-rent-mortgage-rewards.html",
    "snippet": "Gemini unavailable – default relevance.",
    "source": "nytimes.com",
    "time": "2026-01-14T23:10:47+00:00",
    "region": "Global",
    "severity": 2,
    "type": "PHYSICAL SECURITY"
  },
  {
    "title": "Kaiser Permanente Agrees to Pay $556 Million to Settle Medicare Overbilling Claims",
    "url": "https://www.nytimes.com/2026/01/14/health/medicare-advantage-kaiser-overbilling-fraud.html",
    "snippet": "Gemini unavailable – default relevance.",
    "source": "nytimes.com",
    "time": "2026-01-14T23:07:03+00:00",
    "region": "Global",
    "severity": 2,
    "type": "PHYSICAL SECURITY"
  },
  {
    "title": "From behind bars, Aung San Suu Kyi casts a long shadow over Myanmar",
    "url": "https://www.bbc.com/news/articles/c3r197we875o?at_medium=RSS&at_campaign=rss",
    "snippet": "Gemini unavailable – default relevance.",
    "source": "bbc.com",
    "time": "2026-01-14T23:01:28+00:00",
    "region": "Global",
    "severity": 2,
    "type": "PHYSICAL SECURITY"
  },
  {
    "title": "Vance’s Greenland meeting ends with ‘fundamental disagreement’",
    "url": "https://www.washingtonpost.com/national-security/2026/01/14/trump-greenland-jd-vance/",
    "snippet": "Gemini unavailable – default relevance.",
    "source": "washingtonpost.com",
    "time": "2026-01-14T22:52:30+00:00",
    "region": "Global",
    "severity": 2,
    "type": "PHYSICAL SECURITY"
  },
  {
    "title": "OpenAI's hidden ChatGPT Translate tool takes on Google Translate",
    "url": "https://www.bleepingcomputer.com/news/artificial-intelligence/openais-hidden-chatgpt-translate-tool-takes-on-google-translate/",
    "snippet": "Gemini unavailable – default relevance.",
    "source": "bleepingcomputer.com",
    "time": "2026-01-14T22:52:16+00:00",
    "region": "Global",
    "severity": 2,
    "type": "PHYSICAL SECURITY"
  },
  {
    "title": "Abilene Motor Express being absorbed into Swift",
    "url": "https://www.freightwaves.com/news/abilene-motor-express-being-absorbed-into-swift",
    "snippet": "Gemini unavailable – default relevance.",
    "source": "freightwaves.com",
    "time": "2026-01-14T22:50:35+00:00",
    "region": "Global",
    "severity": 2,
    "type": "PHYSICAL SECURITY"
  },
  {
    "title": "Green earthquake (Magnitude 5.6M, Depth:11.617km) in Japan 14/01/2026 22:13 UTC, 270 thousand in MMI IV.",
    "url": "https://www.gdacs.org/report.aspx?eventtype=EQ&eventid=1519524",
    "snippet": "Gemini unavailable – default relevance.",
    "source": "gdacs.org",
    "time": "2026-01-14T22:30:52+00:00",
    "region": "APJC",
    "severity": 2,
    "type": "PHYSICAL SECURITY"
  },
  {
    "title": "Trump’s Gulf Allies Do Not Want Him to Bomb Iran",
    "url": "https://www.nytimes.com/2026/01/14/world/middleeast/gulf-trump-iran.html",
    "snippet": "Gemini unavailable – default relevance.",
    "source": "nytimes.com",
    "time": "2026-01-14T22:26:18+00:00",
    "region": "Global",
    "severity": 2,
    "type": "PHYSICAL SECURITY"
  },
  {
    "title": "Trump says Iran has stopped killings as U.S. weighs military options",
    "url": "https://www.washingtonpost.com/national-security/2026/01/14/us-iran-troops-withdraw-qatar/",
    "snippet": "Gemini unavailable – default relevance.",
    "source": "washingtonpost.com",
    "time": "2026-01-14T22:17:00+00:00",
    "region": "EMEA",
    "severity": 2,
    "type": "PHYSICAL SECURITY"
  },
  {
    "title": "Food Prices Keep Climbing, Rattling Consumers and Trump",
    "url": "https://www.nytimes.com/2026/01/14/business/food-prices-tariffs-trump.html",
    "snippet": "Gemini unavailable – default relevance.",
    "source": "nytimes.com",
    "time": "2026-01-14T22:09:56+00:00",
    "region": "Global",
    "severity": 2,
    "type": "PHYSICAL SECURITY"
  },
  {
    "title": "How Venezuela’s Ghost Fleet Is Surfacing Post-Maduro",
    "url": "https://gcaptain.com/how-venezuelas-ghost-fleet-is-surfacing-post-maduro/",
    "snippet": "Gemini unavailable – default relevance.",
    "source": "gcaptain.com",
    "time": "2026-01-14T21:59:23+00:00",
    "region": "AMER",
    "severity": 2,
    "type": "PHYSICAL SECURITY"
  },
  {
    "title": "South Korean giant Kyowon confirms data theft in ransomware attack",
    "url": "https://www.bleepingcomputer.com/news/security/south-korean-giant-kyowon-confirms-data-theft-in-ransomware-attack/",
    "snippet": "Gemini unavailable – default relevance.",
    "source": "bleepingcomputer.com",
    "time": "2026-01-14T21:49:50+00:00",
    "region": "APJC",
    "severity": 2,
    "type": "PHYSICAL SECURITY"
  },
  {
    "title": "Turkmenistan Rescues 14 Crew From Distressed Iranian Cargo Ship in Caspian Sea",
    "url": "https://gcaptain.com/turkmenistan-rescues-14-crew-from-distressed-iranian-cargo-ship-in-caspian-sea/",
    "snippet": "Gemini unavailable – default relevance.",
    "source": "gcaptain.com",
    "time": "2026-01-14T21:17:52+00:00",
    "region": "Global",
    "severity": 2,
    "type": "PHYSICAL SECURITY"
  },
  {
    "title": "What OOIDA Is Really Fighting For on Right to Repair",
    "url": "https://www.freightwaves.com/news/what-ooida-is-really-fighting-for-on-right-to-repair",
    "snippet": "Gemini unavailable – default relevance.",
    "source": "freightwaves.com",
    "time": "2026-01-14T21:10:40+00:00",
    "region": "Global",
    "severity": 2,
    "type": "PHYSICAL SECURITY"
  },
  {
    "title": "Shipper-turned-carrier integrates with CargoWise to target forwarder business",
    "url": "https://joc.com/article/shipper-turned-carrier-integrates-with-cargowise-to-target-forwarder-business-6152546",
    "snippet": "Gemini unavailable – default relevance.",
    "source": "joc.com",
    "time": "2026-01-14T20:28:14+00:00",
    "region": "Global",
    "severity": 2,
    "type": "PHYSICAL SECURITY"
  },
  {
    "title": "California investigates Grok over AI deepfakes",
    "url": "https://www.bbc.com/news/articles/cpwnqlpw7gxo?at_medium=RSS&at_campaign=rss",
    "snippet": "Gemini unavailable – default relevance.",
    "source": "bbc.com",
    "time": "2026-01-14T20:19:22+00:00",
    "region": "Global",
    "severity": 2,
    "type": "PHYSICAL SECURITY"
  },
  {
    "title": "Saks files for bankruptcy as it struggles to pay debts",
    "url": "https://www.washingtonpost.com/business/2026/01/14/saks-bankruptcy-neiman-marcus-bergdorf/",
    "snippet": "Gemini unavailable – default relevance.",
    "source": "washingtonpost.com",
    "time": "2026-01-14T20:10:56+00:00",
    "region": "Global",
    "severity": 2,
    "type": "PHYSICAL SECURITY"
  },
  {
    "title": "Venezuela releases multiple detained U.S. citizens, State Department says",
    "url": "https://www.washingtonpost.com/world/2026/01/13/venezeula-americans-released-maduro/",
    "snippet": "Gemini unavailable – default relevance.",
    "source": "washingtonpost.com",
    "time": "2026-01-14T20:08:20+00:00",
    "region": "Global",
    "severity": 2,
    "type": "PHYSICAL SECURITY"
  },
  {
    "title": "Heavy haul freight exposes the limits of one-size-fits-all load boards",
    "url": "https://www.freightwaves.com/news/heavy-haul-freight-exposes-the-limits-of-one-size-fits-all-load-boards",
    "snippet": "Gemini unavailable – default relevance.",
    "source": "freightwaves.com",
    "time": "2026-01-14T20:07:07+00:00",
    "region": "AMER",
    "severity": 2,
    "type": "PHYSICAL SECURITY"
  },
  {
    "title": "Green forest fire notification in Central African Republic",
    "url": "https://www.gdacs.org/report.aspx?eventtype=WF&eventid=1026941",
    "snippet": "Gemini unavailable – default relevance.",
    "source": "gdacs.org",
    "time": "2026-01-14T20:00:22+00:00",
    "region": "EMEA",
    "severity": 2,
    "type": "PHYSICAL SECURITY"
  },
  {
    "title": "LTL pricing index hits new high in Q4",
    "url": "https://www.freightwaves.com/news/ltl-pricing-index-hits-new-high-in-q4",
    "snippet": "Gemini unavailable – default relevance.",
    "source": "freightwaves.com",
    "time": "2026-01-14T19:57:11+00:00",
    "region": "AMER",
    "severity": 2,
    "type": "PHYSICAL SECURITY"
  },
  {
    "title": "Proliferation of parcel delivery surcharges drives up shipping rates",
    "url": "https://www.freightwaves.com/news/proliferation-of-parcel-delivery-surcharges-drives-up-shipping-rates",
    "snippet": "Gemini unavailable – default relevance.",
    "source": "freightwaves.com",
    "time": "2026-01-14T19:52:07+00:00",
    "region": "EMEA",
    "severity": 2,
    "type": "PHYSICAL SECURITY"
  },
  {
    "title": "France fines Free Mobile €42 million over 2024 data breach incident",
    "url": "https://www.bleepingcomputer.com/news/security/france-fines-free-mobile-42-million-over-2024-data-breach-incident/",
    "snippet": "Gemini unavailable – default relevance.",
    "source": "bleepingcomputer.com",
    "time": "2026-01-14T19:50:49+00:00",
    "region": "EMEA",
    "severity": 2,
    "type": "PHYSICAL SECURITY"
  },
  {
    "title": "These Gyms’ Most Intimidating Machine: The Front Door",
    "url": "https://www.nytimes.com/2026/01/14/business/puregym-exits-fire-department.html",
    "snippet": "Gemini unavailable – default relevance.",
    "source": "nytimes.com",
    "time": "2026-01-14T19:34:26+00:00",
    "region": "Global",
    "severity": 2,
    "type": "PHYSICAL SECURITY"
  },
  {
    "title": "Venezuela regime claims release of political prisoners is sign of new era",
    "url": "https://www.theguardian.com/world/2026/jan/14/venezuelan-political-prisoners-released",
    "snippet": "Gemini unavailable – default relevance.",
    "source": "theguardian.com",
    "time": "2026-01-14T19:25:00+00:00",
    "region": "Global",
    "severity": 2,
    "type": "PHYSICAL SECURITY"
  },
  {
    "title": "Republicans Advance Stock-Trading Bill With Limited Restrictions",
    "url": "https://www.nytimes.com/2026/01/14/us/politics/republicans-stock-bill-trading.html",
    "snippet": "Gemini unavailable – default relevance.",
    "source": "nytimes.com",
    "time": "2026-01-14T19:19:59+00:00",
    "region": "Global",
    "severity": 2,
    "type": "PHYSICAL SECURITY"
  },
  {
    "title": "Researchers Null-Route Over 550 Kimwolf and Aisuru Botnet Command Servers",
    "url": "https://thehackernews.com/2026/01/kimwolf-botnet-infected-over-2-million.html",
    "snippet": "Gemini unavailable – default relevance.",
    "source": "thehackernews.com",
    "time": "2026-01-14T19:03:00+00:00",
    "region": "Global",
    "severity": 2,
    "type": "PHYSICAL SECURITY"
  },
  {
    "title": "Exploit code public for critical FortiSIEM command injection flaw",
    "url": "https://www.bleepingcomputer.com/news/security/exploit-code-public-for-critical-fortisiem-command-injection-flaw/",
    "snippet": "Gemini unavailable – default relevance.",
    "source": "bleepingcomputer.com",
    "time": "2026-01-14T18:51:54+00:00",
    "region": "Global",
    "severity": 2,
    "type": "PHYSICAL SECURITY"
  },
  {
    "title": "Flat volumes a win for Port of Oakland in unstable year",
    "url": "https://www.freightwaves.com/news/flat-volumes-a-win-for-port-of-oakland-in-unstable-year",
    "snippet": "Gemini unavailable – default relevance.",
    "source": "freightwaves.com",
    "time": "2026-01-14T18:45:11+00:00",
    "region": "APJC",
    "severity": 2,
    "type": "PHYSICAL SECURITY"
  },
  {
    "title": "U.N. Renews Red Sea Reporting Mandate as Russia Needles U.S. on Venezuelan Seizures",
    "url": "https://gcaptain.com/u-n-renews-red-sea-reporting-mandate-as-russia-needles-u-s-on-venezuelan-seizures/",
    "snippet": "Gemini unavailable – default relevance.",
    "source": "gcaptain.com",
    "time": "2026-01-14T18:31:37+00:00",
    "region": "EMEA",
    "severity": 2,
    "type": "PHYSICAL SECURITY"
  },
  {
    "title": "Canada’s Port of Saint John ready for larger ships, more containers",
    "url": "https://joc.com/article/canadas-port-of-saint-john-ready-for-larger-ships-more-containers-6152491",
    "snippet": "Gemini unavailable – default relevance.",
    "source": "joc.com",
    "time": "2026-01-14T17:51:14+00:00",
    "region": "AMER",
    "severity": 2,
    "type": "PHYSICAL SECURITY"
  },
  {
    "title": "Reeves doesn't rule out wider business rates support across hospitality",
    "url": "https://www.bbc.com/news/articles/cn826n1ejl0o?at_medium=RSS&at_campaign=rss",
    "snippet": "Gemini unavailable – default relevance.",
    "source": "bbc.com",
    "time": "2026-01-14T17:38:35+00:00",
    "region": "Global",
    "severity": 2,
    "type": "PHYSICAL SECURITY"
  },
  {
    "title": "Quebec premier François Legault resigns from post in surprise move",
    "url": "https://www.theguardian.com/world/2026/jan/14/quebec-premier-francois-legault-resigns",
    "snippet": "Gemini unavailable – default relevance.",
    "source": "theguardian.com",
    "time": "2026-01-14T17:22:13+00:00",
    "region": "Global",
    "severity": 2,
    "type": "PHYSICAL SECURITY"
  },
  {
    "title": "US Court to Weigh New York Project Challenge to Trump Offshore Wind Halt",
    "url": "https://gcaptain.com/us-court-to-weigh-new-york-project-challenge-to-trump-offshore-wind-halt/",
    "snippet": "Gemini unavailable – default relevance.",
    "source": "gcaptain.com",
    "time": "2026-01-14T17:18:17+00:00",
    "region": "Global",
    "severity": 2,
    "type": "PHYSICAL SECURITY"
  },
  {
    "title": "Russian-Flagged Tanker Seized By U.S. Arrives in UK Waters",
    "url": "https://gcaptain.com/russian-flagged-tanker-seized-by-u-s-arrives-in-uk-waters/",
    "snippet": "Gemini unavailable – default relevance.",
    "source": "gcaptain.com",
    "time": "2026-01-14T17:17:22+00:00",
    "region": "EMEA",
    "severity": 2,
    "type": "PHYSICAL SECURITY"
  },
  {
    "title": "Regional security risk too high to consider Red Sea return: Global shipper group",
    "url": "https://joc.com/article/regional-security-risk-too-high-to-consider-red-sea-return-global-shipper-group-6152469",
    "snippet": "Gemini unavailable – default relevance.",
    "source": "joc.com",
    "time": "2026-01-14T17:09:16+00:00",
    "region": "Global",
    "severity": 2,
    "type": "PHYSICAL SECURITY"
  },
  {
    "title": "Macy’s closes remaining units at Connecticut distribution center",
    "url": "https://www.supplychaindive.com/news/macys-closes-units-at-connecticut-distribution-center/809632/",
    "snippet": "Gemini unavailable – default relevance.",
    "source": "supplychaindive.com",
    "time": "2026-01-14T17:08:36+00:00",
    "region": "Global",
    "severity": 2,
    "type": "PHYSICAL SECURITY"
  },
  {
    "title": "China’s Coal Imports Plunge 10% as Renewable Energy Expansion Reshapes Dry Bulk Shipping",
    "url": "https://gcaptain.com/chinas-coal-imports-plunge-10-as-renewable-energy-expansion-reshapes-dry-bulk-shipping/",
    "snippet": "Gemini unavailable – default relevance.",
    "source": "gcaptain.com",
    "time": "2026-01-14T16:54:46+00:00",
    "region": "APJC",
    "severity": 2,
    "type": "PHYSICAL SECURITY"
  },
  {
    "title": "FMCSA keeps pressure on non-compliant ELD vendors",
    "url": "https://www.freightwaves.com/news/fmcsa-keeps-pressure-on-non-compliant-eld-vendors",
    "snippet": "Gemini unavailable – default relevance.",
    "source": "freightwaves.com",
    "time": "2026-01-14T16:44:27+00:00",
    "region": "AMER",
    "severity": 2,
    "type": "PHYSICAL SECURITY"
  },
  {
    "title": "Why the Northern Powerhouse Rail plan will really go ahead this time",
    "url": "https://www.bbc.com/news/articles/cy7mn3rlggzo?at_medium=RSS&at_campaign=rss",
    "snippet": "Gemini unavailable – default relevance.",
    "source": "bbc.com",
    "time": "2026-01-14T15:58:10+00:00",
    "region": "Global",
    "severity": 2,
    "type": "PHYSICAL SECURITY"
  },
  {
    "title": "Maersk set to resume regular Suez transits on India-USEC ‘MECL’ loop – sources",
    "url": "https://joc.com/article/maersk-set-to-resume-regular-suez-transits-on-india-usec-mecl-loop-sources-6152441",
    "snippet": "Gemini unavailable – default relevance.",
    "source": "joc.com",
    "time": "2026-01-14T15:53:15+00:00",
    "region": "APJC",
    "severity": 2,
    "type": "PHYSICAL SECURITY"
  },
  {
    "title": "AI, tech expand career options for women in supply chain",
    "url": "https://www.supplychaindive.com/news/estee-lauder-company-ai-tech-opportunities-women-in-supply-chain-berenice-vettore/804114/",
    "snippet": "Gemini unavailable – default relevance.",
    "source": "supplychaindive.com",
    "time": "2026-01-14T15:30:00+00:00",
    "region": "Global",
    "severity": 2,
    "type": "PHYSICAL SECURITY"
  },
  {
    "title": "Suspended Michigan autoworker who heckled Trump gets outpouring of donations",
    "url": "https://www.theguardian.com/us-news/2026/jan/14/trump-suspended-michigan-autoworker",
    "snippet": "Gemini unavailable – default relevance.",
    "source": "theguardian.com",
    "time": "2026-01-14T15:23:33+00:00",
    "region": "AMER",
    "severity": 2,
    "type": "PHYSICAL SECURITY"
  },
  {
    "title": "Hiring declines as employers take cautious view of new year",
    "url": "https://www.supplychaindive.com/news/hiring-declines-employers-take-cautious-view-new-year-employment-unemployment-Fed/809347/",
    "snippet": "Gemini unavailable – default relevance.",
    "source": "supplychaindive.com",
    "time": "2026-01-14T15:21:47+00:00",
    "region": "Global",
    "severity": 2,
    "type": "PHYSICAL SECURITY"
  },
  {
    "title": "Why Greenland Matters for a Warming World",
    "url": "https://www.nytimes.com/2026/01/14/world/europe/greenland-climate.html",
    "snippet": "Gemini unavailable – default relevance.",
    "source": "nytimes.com",
    "time": "2026-01-14T15:16:10+00:00",
    "region": "EMEA",
    "severity": 2,
    "type": "PHYSICAL SECURITY"
  },
  {
    "title": "AI Agents Are Becoming Authorization Bypass Paths",
    "url": "https://thehackernews.com/2026/01/ai-agents-are-becoming-privilege.html",
    "snippet": "Gemini unavailable – default relevance.",
    "source": "thehackernews.com",
    "time": "2026-01-14T15:07:00+00:00",
    "region": "Global",
    "severity": 2,
    "type": "PHYSICAL SECURITY"
  },
  {
    "title": "TGI Fridays closes 16 UK stores, with 456 job losses",
    "url": "https://www.bbc.com/news/articles/cz7yl53e11do?at_medium=RSS&at_campaign=rss",
    "snippet": "Gemini unavailable – default relevance.",
    "source": "bbc.com",
    "time": "2026-01-14T14:57:23+00:00",
    "region": "EMEA",
    "severity": 2,
    "type": "PHYSICAL SECURITY"
  },
  {
    "title": "Green notification for tropical cyclone NOKAEN-26. Population affected by Category 1 (120 km/h) wind speeds or higher is 0  (0 in Tropical Storm).",
    "url": "https://www.gdacs.org/report.aspx?eventtype=TC&eventid=1001249",
    "snippet": "Gemini unavailable – default relevance.",
    "source": "gdacs.org",
    "time": "2026-01-14T14:36:27+00:00",
    "region": "APJC",
    "severity": 2,
    "type": "PHYSICAL SECURITY"
  },
  {
    "title": "Hackers Exploit c-ares DLL Side-Loading to Bypass Security and Deploy Malware",
    "url": "https://thehackernews.com/2026/01/hackers-exploit-c-ares-dll-side-loading.html",
    "snippet": "Gemini unavailable – default relevance.",
    "source": "thehackernews.com",
    "time": "2026-01-14T14:18:00+00:00",
    "region": "Global",
    "severity": 2,
    "type": "PHYSICAL SECURITY"
  },
  {
    "title": "Air cargo shippers take short-term contract approach to close 2025",
    "url": "https://www.supplychaindive.com/news/air-cargo-contract-behavior-shifts-rates-ecommerce-xeneta/809284/",
    "snippet": "Gemini unavailable – default relevance.",
    "source": "supplychaindive.com",
    "time": "2026-01-14T14:05:04+00:00",
    "region": "Global",
    "severity": 2,
    "type": "PHYSICAL SECURITY"
  },
  {
    "title": "USPS eyes expanding package dimension reporting requirements",
    "url": "https://www.supplychaindive.com/news/us-postal-service-dimensional-reporting-change/809511/",
    "snippet": "Gemini unavailable – default relevance.",
    "source": "supplychaindive.com",
    "time": "2026-01-14T13:41:00+00:00",
    "region": "Global",
    "severity": 2,
    "type": "PHYSICAL SECURITY"
  },
  {
    "title": "Hookham: ‘This is the year the container lines will see a reckoning’",
    "url": "https://theloadstar.com/this-is-the-year-the-container-lines-will-see-a-reckoning/",
    "snippet": "Gemini unavailable – default relevance.",
    "source": "theloadstar.com",
    "time": "2026-01-14T13:37:03+00:00",
    "region": "Global",
    "severity": 2,
    "type": "PHYSICAL SECURITY"
  },
  {
    "title": "Venezuelan Oil Exports to China Set to Drop as US Blockade Limits Cargoes",
    "url": "https://gcaptain.com/venezuelan-oil-exports-to-china-set-to-drop-as-us-blockade-limits-cargoes/",
    "snippet": "Gemini unavailable – default relevance.",
    "source": "gcaptain.com",
    "time": "2026-01-14T12:45:42+00:00",
    "region": "APJC",
    "severity": 2,
    "type": "PHYSICAL SECURITY"
  },
  {
    "title": "Dark Fleet Seeking Russian Protection as US Seizes Oil Tankers",
    "url": "https://gcaptain.com/dark-fleet-seeking-russian-protection-as-us-seizes-oil-tankers/",
    "snippet": "Gemini unavailable – default relevance.",
    "source": "gcaptain.com",
    "time": "2026-01-14T12:36:30+00:00",
    "region": "EMEA",
    "severity": 2,
    "type": "PHYSICAL SECURITY"
  },
  {
    "title": "Secure Connectivity Principles for Operational Technology (OT)",
    "url": "https://www.cisa.gov/resources-tools/resources/secure-connectivity-principles-operational-technology-ot",
    "snippet": "Gemini unavailable – default relevance.",
    "source": "cisa.gov",
    "time": "2026-01-14T12:00:00+00:00",
    "region": "EMEA",
    "severity": 2,
    "type": "PHYSICAL SECURITY"
  },
  {
    "title": "Fortinet Fixes Critical FortiSIEM Flaw Allowing Unauthenticated Remote Code Execution",
    "url": "https://thehackernews.com/2026/01/fortinet-fixes-critical-fortisiem-flaw.html",
    "snippet": "Gemini unavailable – default relevance.",
    "source": "thehackernews.com",
    "time": "2026-01-14T11:53:00+00:00",
    "region": "Global",
    "severity": 2,
    "type": "PHYSICAL SECURITY"
  },
  {
    "title": "Something Bad Is Brewing on Venezuela’s Border",
    "url": "https://www.crisisgroup.org/latin-america-caribbean/venezuela-colombia-united-states/something-bad-brewing-venezuelas-border",
    "snippet": "Gemini unavailable – default relevance.",
    "source": "crisisgroup.org",
    "time": "2026-01-14T11:48:54+00:00",
    "region": "APJC",
    "severity": 2,
    "type": "PHYSICAL SECURITY"
  },
  {
    "title": "You don’t need Trump to cap your credit card interest. Just use this script.",
    "url": "https://www.washingtonpost.com/business/2026/01/14/trump-credit-card-interest-cap-how-to-lower/",
    "snippet": "Gemini unavailable – default relevance.",
    "source": "washingtonpost.com",
    "time": "2026-01-14T11:00:56+00:00",
    "region": "Global",
    "severity": 2,
    "type": "PHYSICAL SECURITY"
  },
  {
    "title": "Union leaders accuse Trump labor department of echoing Nazi rhetoric",
    "url": "https://www.theguardian.com/us-news/2026/jan/14/union-leaders-trump-administration-white-supremacy",
    "snippet": "Gemini unavailable – default relevance.",
    "source": "theguardian.com",
    "time": "2026-01-14T11:00:23+00:00",
    "region": "AMER",
    "severity": 2,
    "type": "PHYSICAL SECURITY"
  },
  {
    "title": "New Research: 64% of 3rd-Party Applications Access Sensitive Data Without Justification",
    "url": "https://thehackernews.com/2026/01/new-research-64-of-3rd-party.html",
    "snippet": "Gemini unavailable – default relevance.",
    "source": "thehackernews.com",
    "time": "2026-01-14T11:00:00+00:00",
    "region": "Global",
    "severity": 2,
    "type": "PHYSICAL SECURITY"
  },
  {
    "title": "We analyzed hundreds of earnings calls to see what executives really think of the economy",
    "url": "https://www.washingtonpost.com/business/interactive/2026/corporate-earnings-calls-economic-optimism/",
    "snippet": "Gemini unavailable – default relevance.",
    "source": "washingtonpost.com",
    "time": "2026-01-14T10:00:51+00:00",
    "region": "Global",
    "severity": 2,
    "type": "PHYSICAL SECURITY"
  },
  {
    "title": "Stars and Stripes job applicants are asked if they back Trump policies",
    "url": "https://www.washingtonpost.com/business/2026/01/14/stars-and-stripes-trump-loyalty-test/",
    "snippet": "Gemini unavailable – default relevance.",
    "source": "washingtonpost.com",
    "time": "2026-01-14T10:00:49+00:00",
    "region": "Global",
    "severity": 2,
    "type": "PHYSICAL SECURITY"
  },
  {
    "title": "Boomers are staying in the job market as Gen Z struggles to break through",
    "url": "https://www.washingtonpost.com/business/2026/01/14/workers-age-new-jobs-baby-boomers/",
    "snippet": "Gemini unavailable – default relevance.",
    "source": "washingtonpost.com",
    "time": "2026-01-14T10:00:00+00:00",
    "region": "Global",
    "severity": 2,
    "type": "PHYSICAL SECURITY"
  },
  {
    "title": "Parents are cutting back on child care as costs stretch budgets",
    "url": "https://www.washingtonpost.com/business/2026/01/14/child-care-cost-cuts/",
    "snippet": "Gemini unavailable – default relevance.",
    "source": "washingtonpost.com",
    "time": "2026-01-14T10:00:00+00:00",
    "region": "Global",
    "severity": 2,
    "type": "PHYSICAL SECURITY"
  },
  {
    "title": "Microsoft Fixes 114 Windows Flaws in January 2026 Patch, One Actively Exploited",
    "url": "https://thehackernews.com/2026/01/microsoft-fixes-114-windows-flaws-in.html",
    "snippet": "Gemini unavailable – default relevance.",
    "source": "thehackernews.com",
    "time": "2026-01-14T09:38:00+00:00",
    "region": "Global",
    "severity": 2,
    "type": "PHYSICAL SECURITY"
  },
  {
    "title": "Economic conflicts are world’s greatest risk, WEF survey suggests",
    "url": "https://www.theguardian.com/business/2026/jan/14/economic-conflicts-are-worlds-greatest-risk-wef-survey-suggests",
    "snippet": "Gemini unavailable – default relevance.",
    "source": "theguardian.com",
    "time": "2026-01-14T09:15:20+00:00",
    "region": "Global",
    "severity": 2,
    "type": "PHYSICAL SECURITY"
  },
  {
    "title": "Netflix ‘plans to switch to all-cash offer to seal $83bn Warner Bros deal’",
    "url": "https://www.theguardian.com/film/2026/jan/14/netflix-plans-to-switch-to-all-cash-offer-to-seal-warner-bros-deal",
    "snippet": "Gemini unavailable – default relevance.",
    "source": "theguardian.com",
    "time": "2026-01-14T09:12:22+00:00",
    "region": "Global",
    "severity": 2,
    "type": "PHYSICAL SECURITY"
  },
  {
    "title": "Critical Node.js Vulnerability Can Cause Server Crashes via async_hooks Stack Overflow",
    "url": "https://thehackernews.com/2026/01/critical-nodejs-vulnerability-can-cause.html",
    "snippet": "Gemini unavailable – default relevance.",
    "source": "thehackernews.com",
    "time": "2026-01-14T07:05:00+00:00",
    "region": "Global",
    "severity": 2,
    "type": "PHYSICAL SECURITY"
  },
  {
    "title": "Iraq 12 January 2026",
    "url": "https://www.crisisgroup.org/content/iraq-12-january-2026",
    "snippet": "Gemini unavailable – default relevance.",
    "source": "crisisgroup.org",
    "time": "2026-01-13T23:44:31+00:00",
    "region": "AMER",
    "severity": 2,
    "type": "PHYSICAL SECURITY"
  },
  {
    "title": "Tehran 12 January 2026",
    "url": "https://www.crisisgroup.org/content/tehran-12-january-2026",
    "snippet": "Gemini unavailable – default relevance.",
    "source": "crisisgroup.org",
    "time": "2026-01-13T23:42:52+00:00",
    "region": "Global",
    "severity": 2,
    "type": "PHYSICAL SECURITY"
  },
  {
    "title": "Washington 13 January 2026 #1",
    "url": "https://www.crisisgroup.org/content/washington-13-january-2026-1",
    "snippet": "Gemini unavailable – default relevance.",
    "source": "crisisgroup.org",
    "time": "2026-01-13T23:42:11+00:00",
    "region": "Global",
    "severity": 2,
    "type": "PHYSICAL SECURITY"
  },
  {
    "title": "Trump claims victory on US economy despite many Americans’ cost of living concerns",
    "url": "https://www.theguardian.com/business/2026/jan/13/trump-economy-cost-of-living",
    "snippet": "Gemini unavailable – default relevance.",
    "source": "theguardian.com",
    "time": "2026-01-13T23:02:14+00:00",
    "region": "AMER",
    "severity": 2,
    "type": "PHYSICAL SECURITY"
  },
  {
    "title": "Trump administration ends temporary protected status for Somalis in US",
    "url": "https://www.theguardian.com/us-news/2026/jan/13/trump-administration-ends-tps-somalia",
    "snippet": "Gemini unavailable – default relevance.",
    "source": "theguardian.com",
    "time": "2026-01-13T22:59:07+00:00",
    "region": "EMEA",
    "severity": 2,
    "type": "PHYSICAL SECURITY"
  },
  {
    "title": "4PL model reemerges as disruptive market dynamics buffet shippers",
    "url": "https://joc.com/article/4pl-model-reemerges-as-disruptive-market-dynamics-buffet-shippers-6152066",
    "snippet": "Gemini unavailable – default relevance.",
    "source": "joc.com",
    "time": "2026-01-13T20:40:14+00:00",
    "region": "Global",
    "severity": 2,
    "type": "PHYSICAL SECURITY"
  },
  {
    "title": "Aldi to open 3 distribution centers by 2029",
    "url": "https://www.supplychaindive.com/news/aldi-three-distribution-centers-colordao-florida-arizona-2029/809371/",
    "snippet": "Gemini unavailable – default relevance.",
    "source": "supplychaindive.com",
    "time": "2026-01-13T19:29:04+00:00",
    "region": "Global",
    "severity": 2,
    "type": "PHYSICAL SECURITY"
  },
  {
    "title": "Cosco inks almost $2.7 billion in deals for 18 newbuild container ships",
    "url": "https://joc.com/article/cosco-inks-almost-27-billion-in-deals-for-18-newbuild-container-ships-6152035",
    "snippet": "Gemini unavailable – default relevance.",
    "source": "joc.com",
    "time": "2026-01-13T18:59:15+00:00",
    "region": "Global",
    "severity": 2,
    "type": "PHYSICAL SECURITY"
  },
  {
    "title": "‘Unexpected’ margin boost in Q3 2025 to lift ocean carriers’ full-year results – Drewry",
    "url": "https://joc.com/article/unexpected-margin-boost-in-q3-2025-to-lift-ocean-carriers-full-year-results-drewry-6151976",
    "snippet": "Gemini unavailable – default relevance.",
    "source": "joc.com",
    "time": "2026-01-13T16:53:15+00:00",
    "region": "Global",
    "severity": 2,
    "type": "PHYSICAL SECURITY"
  },
  {
    "title": "U.S. lost more immigrants than it gained in 2025, new estimate shows",
    "url": "https://www.washingtonpost.com/business/2026/01/13/trump-immigration-economy-net-negative-migration/",
    "snippet": "Gemini unavailable – default relevance.",
    "source": "washingtonpost.com",
    "time": "2026-01-13T15:43:02+00:00",
    "region": "Global",
    "severity": 2,
    "type": "PHYSICAL SECURITY"
  },
  {
    "title": "Quarter of developing countries poorer than in 2019, World Bank finds",
    "url": "https://www.theguardian.com/business/2026/jan/13/developing-countries-poorer-world-bank-report",
    "snippet": "Gemini unavailable – default relevance.",
    "source": "theguardian.com",
    "time": "2026-01-13T14:30:04+00:00",
    "region": "EMEA",
    "severity": 2,
    "type": "PHYSICAL SECURITY"
  },
  {
    "title": "2026 hiring outlook improves, but skills and AI are primary hurdles",
    "url": "https://www.supplychaindive.com/news/2026-hiring-outlook-improves-skills-ai-hurdles/809238/",
    "snippet": "Gemini unavailable – default relevance.",
    "source": "supplychaindive.com",
    "time": "2026-01-13T14:25:04+00:00",
    "region": "Global",
    "severity": 2,
    "type": "PHYSICAL SECURITY"
  },
  {
    "title": "Global central banks offer ‘full solidarity’ to US Fed’s Powell amid Trump threats",
    "url": "https://www.theguardian.com/business/2026/jan/13/central-banks-us-fed-powell-trump-bank-of-england-ecb",
    "snippet": "Gemini unavailable – default relevance.",
    "source": "theguardian.com",
    "time": "2026-01-13T13:50:18+00:00",
    "region": "EMEA",
    "severity": 2,
    "type": "PHYSICAL SECURITY"
  },
  {
    "title": "Trump threatens 25% tariff on Iran’s trading partners",
    "url": "https://www.supplychaindive.com/news/trump-tariffs-iran-trading-partners/809468/",
    "snippet": "Gemini unavailable – default relevance.",
    "source": "supplychaindive.com",
    "time": "2026-01-13T12:58:00+00:00",
    "region": "Global",
    "severity": 2,
    "type": "PHYSICAL SECURITY"
  },
  {
    "title": "Rockwell Automation 432ES-IG3 Series A",
    "url": "https://www.cisa.gov/news-events/ics-advisories/icsa-26-013-01",
    "snippet": "Gemini unavailable – default relevance.",
    "source": "cisa.gov",
    "time": "2026-01-13T12:00:00+00:00",
    "region": "AMER",
    "severity": 2,
    "type": "PHYSICAL SECURITY"
  },
  {
    "title": "Rockwell Automation FactoryTalk DataMosaix Private Cloud",
    "url": "https://www.cisa.gov/news-events/ics-advisories/icsa-26-013-02",
    "snippet": "Gemini unavailable – default relevance.",
    "source": "cisa.gov",
    "time": "2026-01-13T12:00:00+00:00",
    "region": "AMER",
    "severity": 2,
    "type": "PHYSICAL SECURITY"
  },
  {
    "title": "CISA Adds One Known Exploited Vulnerability to Catalog",
    "url": "https://www.cisa.gov/news-events/alerts/2026/01/13/cisa-adds-one-known-exploited-vulnerability-catalog",
    "snippet": "Gemini unavailable – default relevance.",
    "source": "cisa.gov",
    "time": "2026-01-13T12:00:00+00:00",
    "region": "Global",
    "severity": 2,
    "type": "PHYSICAL SECURITY"
  },
  {
    "title": "YoSmart YoLink Smart Hub",
    "url": "https://www.cisa.gov/news-events/ics-advisories/icsa-26-013-03",
    "snippet": "Gemini unavailable – default relevance.",
    "source": "cisa.gov",
    "time": "2026-01-13T12:00:00+00:00",
    "region": "AMER",
    "severity": 2,
    "type": "PHYSICAL SECURITY"
  },
  {
    "title": "Jerome Powell: steely Fed chair standing firm in face of Trump’s threats",
    "url": "https://www.theguardian.com/business/2026/jan/13/jerome-powell-fed-chair-trump",
    "snippet": "Gemini unavailable – default relevance.",
    "source": "theguardian.com",
    "time": "2026-01-13T11:00:59+00:00",
    "region": "Global",
    "severity": 2,
    "type": "PHYSICAL SECURITY"
  },
  {
    "title": "Green earthquake (Magnitude 6.2M, Depth:35.788km) in Russia 13/01/2026 07:34 UTC, 6 thousand in MMI IV.",
    "url": "https://www.gdacs.org/report.aspx?eventtype=EQ&eventid=1519282",
    "snippet": "Gemini unavailable – default relevance.",
    "source": "gdacs.org",
    "time": "2026-01-13T07:54:58+00:00",
    "region": "EMEA",
    "severity": 2,
    "type": "PHYSICAL SECURITY"
  },
  {
    "title": "Green earthquake (Magnitude 5.6M, Depth:10km) in Easter Island Region 13/01/2026 03:39 UTC, [unknown].",
    "url": "https://www.gdacs.org/report.aspx?eventtype=EQ&eventid=1519260",
    "snippet": "Gemini unavailable – default relevance.",
    "source": "gdacs.org",
    "time": "2026-01-13T04:00:09+00:00",
    "region": "Global",
    "severity": 2,
    "type": "PHYSICAL SECURITY"
  },
  {
    "title": "SeaCube acquires Martin Container in move to boost West Coast cold storage",
    "url": "https://joc.com/article/seacube-acquires-martin-container-in-move-to-boost-west-coast-cold-storage-6150875",
    "snippet": "Gemini unavailable – default relevance.",
    "source": "joc.com",
    "time": "2026-01-12T22:05:15+00:00",
    "region": "Global",
    "severity": 2,
    "type": "PHYSICAL SECURITY"
  },
  {
    "title": "Hapag-Lloyd’s terminal arm takes full control of terminal at Port Everglades",
    "url": "https://joc.com/article/hapag-lloyds-terminal-arm-takes-full-control-of-terminal-at-port-everglades-6150762",
    "snippet": "Gemini unavailable – default relevance.",
    "source": "joc.com",
    "time": "2026-01-12T19:50:15+00:00",
    "region": "Global",
    "severity": 2,
    "type": "PHYSICAL SECURITY"
  },
  {
    "title": "Trump admin clarifies scope of tariff refunds ahead of Supreme Court ruling",
    "url": "https://www.supplychaindive.com/news/tariff-refunds-ieepa-supreme-court/809359/",
    "snippet": "Gemini unavailable – default relevance.",
    "source": "supplychaindive.com",
    "time": "2026-01-12T16:05:37+00:00",
    "region": "APJC",
    "severity": 2,
    "type": "PHYSICAL SECURITY"
  },
  {
    "title": "Sendle, ACI Logistix and FirstMile parent Fast Group to close",
    "url": "https://www.supplychaindive.com/news/sendle-aci-logistix-firstmile-fast-group-shut-down/809356/",
    "snippet": "Gemini unavailable – default relevance.",
    "source": "supplychaindive.com",
    "time": "2026-01-12T16:02:40+00:00",
    "region": "Global",
    "severity": 2,
    "type": "PHYSICAL SECURITY"
  },
  {
    "title": "Author Chimamanda Ngozi Adichie accuses Lagos hospital of negligence after son’s death",
    "url": "https://www.theguardian.com/books/2026/jan/12/chimamanda-ngozi-adichie-accuses-lagos-hospital-negligence-son-death",
    "snippet": "Gemini unavailable – default relevance.",
    "source": "theguardian.com",
    "time": "2026-01-12T14:26:57+00:00",
    "region": "Global",
    "severity": 2,
    "type": "PHYSICAL SECURITY"
  },
  {
    "title": "Attempt to overturn the Gambia’s ban on FGM heard by supreme court",
    "url": "https://www.theguardian.com/global-development/2026/jan/09/the-gambia-female-genital-mutilation-fgm-supreme-court-case-overturn-ban",
    "snippet": "Gemini unavailable – default relevance.",
    "source": "theguardian.com",
    "time": "2026-01-09T06:00:29+00:00",
    "region": "Global",
    "severity": 2,
    "type": "PHYSICAL SECURITY"
  },
  {
    "title": "Hitachi Energy Asset Suite",
    "url": "https://www.cisa.gov/news-events/ics-advisories/icsa-26-008-01",
    "snippet": "Gemini unavailable – default relevance.",
    "source": "cisa.gov",
    "time": "2026-01-08T12:00:00+00:00",
    "region": "Global",
    "severity": 2,
    "type": "PHYSICAL SECURITY"
  },
  {
    "title": "CISA Adds Two Known Exploited Vulnerabilities to Catalog",
    "url": "https://www.cisa.gov/news-events/alerts/2026/01/07/cisa-adds-two-known-exploited-vulnerabilities-catalog",
    "snippet": "Gemini unavailable – default relevance.",
    "source": "cisa.gov",
    "time": "2026-01-07T12:00:00+00:00",
    "region": "Global",
    "severity": 2,
    "type": "PHYSICAL SECURITY"
  },
  {
    "title": "Columbia Weather Systems MicroServer",
    "url": "https://www.cisa.gov/news-events/ics-advisories/icsa-26-006-01",
    "snippet": "Gemini unavailable – default relevance.",
    "source": "cisa.gov",
    "time": "2026-01-06T12:00:00+00:00",
    "region": "AMER",
    "severity": 2,
    "type": "PHYSICAL SECURITY"
  },
  {
    "title": "CISA Releases Two Industrial Control Systems Advisories",
    "url": "https://www.cisa.gov/news-events/alerts/2025/12/30/cisa-releases-two-industrial-control-systems-advisories",
    "snippet": "Gemini unavailable – default relevance.",
    "source": "cisa.gov",
    "time": "2025-12-30T12:00:00+00:00",
    "region": "Global",
    "severity": 2,
    "type": "PHYSICAL SECURITY"
  }
]